{
  "profile": {},
  "samples": [
    {
      "t": 0.0,
      "t_abs": "2026-01-16T08:13:10Z",
      "lat_deg": null,
      "lon_deg": null,
      "v_ms": 0.0,
      "altitude_m": 0.0,
      "grade": 0.0,
      "heading_deg": 0.0,
      "hr": null,
      "moving": true
    },
    {
      "t": 2874.0,
      "t_abs": "2026-01-16T09:01:04Z",
      "lat_deg": null,
      "lon_deg": null,
      "v_ms": 0.0,
      "altitude_m": 0.0,
      "grade": 0.0,
      "heading_deg": 0.0,
      "hr": null,
      "moving": true
    }
  ],
  "weather_hint": {},
  "strava": {
    "activity_id": "17067166485",
    "mode": "indoor",
    "start_date": "2026-01-16T08:13:10Z"
  }
}