{
  "calibrated": false,
  "cg_build": "T15-cg_build-20251216",
  "metrics": {
    "cg_build": "T15-cg_build-20251216",
    "core_n_device_samples": 0,
    "core_watts_source": "disabled_no_powermeter",
    "drag_watt": 135.88270498606215,
    "eff_used": 0.5,
    "gravity_watt": 0.004353276178264513,
    "gravity_watt_pedal": 59.56088111257871,
    "model_watt_crank": 331.14408769002154,
    "model_watt_wheel": 165.57204384501077,
    "model_watt_wheel_pedal": 226.3202911481718,
    "model_watt_wheel_pedal_elapsed": 224.70173600425284,
    "model_watt_wheel_pedal_moving": 226.3202911481718,
    "pedal_ratio_elapsed_over_moving": 0.992848386966508,
    "precision_watt": 173.37386790053483,
    "precision_watt_avg": 165.57204384501077,
    "precision_watt_crank": 331.14408769002154,
    "precision_watt_pedal": 235.75030327934564,
    "profile_used": {
      "rider_weight_kg": 85,
      "bike_weight_kg": 8.0,
      "weight_kg": 93.0,
      "total_weight_kg": 93.0,
      "bike_type": "road",
      "tire_width_mm": 28,
      "tire_quality": "performance",
      "device": "strava",
      "profile_version": "v1-5403a6cd-20260101",
      "cda": 0.3,
      "crr": 0.004,
      "crank_efficiency": 0.96
    },
    "rolling_watt": 29.684985582770327,
    "total_watt": 165.57204384501077,
    "total_watt_pedal": 226.3202911481718,
    "wind_effect": 0.55,
    "precision_watt_signed": 165.57204384501077,
    "total_watt_signed": 165.57204384501077,
    "gravity_watt_signed": 0.004353276178264513,
    "model_watt_wheel_signed": 165.57204384501077,
    "calibration_mae": null,
    "calibrated": false,
    "calibration_status": "not_available",
    "estimated_error_pct_range": [
      null,
      null
    ],
    "precision_quality_hint": "no-heuristics-available",
    "weather_applied": false
  },
  "precision_watt_avg": 235.75030327934564,
  "source": "rust_1arg",
  "v_rel": [
    0.1,
    0.1,
    0.1,
    0.1,
    7.66,
    7.98,
    8.2,
    8.683,
    8.92,
    8.817,
    8.3,
    8.3,
    8.36,
    8.233,
    7.98,
    7.867,
    7.8,
    7.42,
    7.35,
    7.08,
    6.74,
    6.66,
    6.58,
    6.583,
    6.68,
    6.64,
    6.55,
    6.692,
    6.789,
    6.78,
    6.773,
    6.78,
    6.729,
    6.656,
    6.614,
    6.362,
    6.386,
    6.84,
    7.356,
    8.158,
    8.429,
    8.743,
    8.789,
    8.825,
    9.0,
    8.833,
    8.725,
    8.825,
    8.636,
    8.408,
    8.314,
    8.267,
    7.65,
    7.414,
    7.325,
    7.189,
    5.68,
    5.18,
    4.383,
    5.371,
    6.42,
    6.886,
    8.46,
    8.94,
    9.689,
    9.917,
    10.071,
    10.033,
    9.933,
    9.8,
    9.783,
    9.69,
    9.508,
    9.033,
    8.8,
    8.688,
    8.662,
    8.622,
    8.58,
    8.878,
    9.111,
    9.127,
    9.138,
    9.42,
    9.675,
    9.92,
    9.988,
    10.038,
    9.783,
    9.557,
    8.844,
    8.492,
    7.925,
    7.878,
    7.557,
    7.589,
    7.517,
    7.6,
    7.8,
    7.714,
    7.54,
    7.56,
    7.6,
    8.144,
    8.708,
    9.257,
    9.3,
    9.733,
    9.8,
    9.462,
    9.35,
    9.244,
    9.313,
    9.367,
    9.555,
    10.24,
    10.46,
    10.58,
    10.5,
    10.04,
    9.56,
    9.14,
    8.767,
    8.6,
    9.05,
    9.386,
    9.467,
    9.589,
    9.578,
    9.59,
    10.029,
    9.738,
    9.74,
    9.3,
    9.717,
    9.7,
    9.72,
    9.733,
    9.69,
    9.627,
    9.578,
    9.23,
    9.09,
    9.122,
    9.175,
    9.144,
    8.91,
    8.74,
    8.56,
    8.567,
    8.58,
    8.667,
    8.788,
    9.038,
    9.05,
    9.35,
    9.375,
    9.467,
    9.489,
    9.508,
    9.575,
    9.62,
    9.844,
    9.83,
    9.57,
    9.462,
    9.433,
    9.22,
    8.686,
    8.233,
    8.175,
    7.717,
    7.343,
    7.0,
    6.986,
    6.783,
    6.2,
    6.2,
    6.217,
    6.517,
    6.68,
    6.84,
    7.014,
    7.42,
    7.783,
    7.88,
    7.84,
    7.8,
    7.66,
    7.62,
    7.82,
    7.817,
    7.76,
    7.857,
    8.12,
    8.129,
    8.2,
    8.3,
    8.3,
    8.233,
    7.94,
    7.95,
    8.711,
    8.987,
    9.291,
    10.2,
    10.34,
    10.467,
    10.5,
    10.62,
    10.667,
    10.72,
    10.84,
    10.88,
    10.986,
    11.233,
    11.112,
    10.94,
    10.629,
    9.6,
    9.3,
    9.3,
    10.38,
    11.117,
    11.78,
    11.9,
    12.4,
    12.28,
    12.08,
    11.933,
    11.3,
    10.8,
    10.08,
    9.917,
    9.36,
    8.16,
    7.757,
    7.22,
    7.133,
    6.7,
    6.557,
    6.936,
    7.175,
    7.56,
    7.386,
    6.76,
    6.6,
    6.357,
    5.367,
    4.86,
    4.62,
    4.533,
    4.233,
    4.207,
    4.244,
    4.011,
    3.883,
    3.767,
    3.85,
    3.794,
    3.711,
    3.66,
    3.722,
    3.786,
    3.58,
    3.55,
    3.543,
    3.583,
    3.7,
    3.767,
    3.629,
    4.133,
    4.88,
    5.071,
    5.05,
    4.84,
    4.75,
    4.76,
    4.76,
    4.76,
    5.16,
    5.5,
    6.48,
    7.06,
    7.817,
    7.445,
    7.0,
    6.867,
    6.6,
    5.24,
    5.2,
    5.071,
    4.9,
    4.857,
    4.7,
    4.767,
    4.967,
    5.0,
    5.15,
    5.37,
    5.9,
    5.783,
    5.888,
    6.32,
    6.725,
    6.829,
    7.55,
    7.738,
    8.022,
    8.17,
    8.42,
    8.338,
    8.2,
    8.143,
    8.133,
    8.16,
    8.243,
    8.54,
    8.64,
    8.514,
    8.4,
    8.433,
    8.46,
    9.12,
    9.514,
    9.771,
    9.857,
    9.9,
    10.13,
    10.3,
    10.39,
    10.671,
    10.54,
    10.333,
    10.32,
    10.2,
    9.76,
    9.65,
    9.475,
    9.05,
    8.66,
    8.26,
    7.92,
    7.667,
    7.55,
    7.383,
    7.4,
    7.34,
    7.4,
    7.55,
    7.64,
    7.82,
    8.1,
    8.2,
    8.32,
    8.34,
    8.75,
    9.056,
    9.9,
    10.138,
    10.21,
    10.517,
    10.533,
    10.58,
    10.7,
    10.845,
    11.037,
    11.18,
    11.513,
    11.571,
    11.563,
    11.586,
    11.586,
    11.44,
    11.433,
    10.843,
    10.517,
    10.567,
    10.68,
    10.667,
    10.586,
    10.367,
    9.7,
    9.467,
    9.6,
    10.12,
    10.533,
    12.3,
    12.6,
    12.867,
    13.043,
    13.64,
    14.04,
    14.233,
    15.1,
    15.32,
    15.7,
    16.02,
    15.933,
    15.857,
    15.56,
    15.467,
    15.371,
    14.56,
    14.4,
    14.286,
    14.125,
    13.46,
    13.117,
    12.08,
    11.3,
    9.28,
    9.08,
    8.36,
    8.14,
    8.05,
    6.82,
    6.567,
    6.0,
    5.457,
    5.35,
    4.9,
    4.62,
    4.429,
    4.26,
    4.2,
    4.16,
    4.263,
    4.214,
    4.1,
    3.825,
    3.4,
    3.325,
    3.06,
    3.274,
    3.462,
    3.611,
    3.831,
    4.136,
    4.6,
    4.88,
    5.043,
    5.383,
    5.767,
    6.04,
    6.48,
    6.533,
    6.8,
    7.28,
    7.98,
    8.227,
    8.433,
    8.8,
    8.862,
    8.82,
    8.58,
    8.617,
    8.671,
    9.05,
    9.15,
    9.462,
    9.313,
    9.1,
    8.52,
    8.55,
    8.32,
    8.088,
    7.917,
    7.96,
    8.364,
    9.013,
    9.933,
    10.46,
    10.725,
    10.79,
    10.96,
    10.867,
    10.68,
    10.38,
    10.14,
    9.76,
    9.122,
    8.409,
    7.79,
    7.75,
    7.745,
    7.711,
    7.582,
    6.5,
    6.14,
    6.071,
    5.74,
    5.7,
    5.36,
    4.98,
    4.84,
    4.76,
    4.68,
    4.6,
    4.614,
    4.717,
    4.84,
    4.8,
    4.889,
    5.017,
    5.175,
    5.117,
    5.16,
    5.18,
    5.22,
    5.267,
    5.338,
    5.48,
    5.5,
    5.533,
    5.64,
    6.157,
    6.313,
    6.783,
    6.873,
    6.925,
    7.44,
    7.7,
    7.86,
    8.057,
    8.0,
    8.2,
    8.356,
    8.38,
    8.0,
    8.0,
    8.063,
    8.286,
    8.525,
    8.65,
    8.65,
    8.688,
    8.817,
    8.686,
    8.638,
    8.167,
    8.15,
    8.43,
    8.82,
    9.75,
    10.417,
    11.017,
    11.433,
    11.58,
    11.68,
    11.9,
    12.017,
    12.42,
    12.657,
    12.714,
    12.42,
    12.214,
    11.84,
    11.76,
    12.2,
    12.429,
    12.313,
    12.071,
    11.9,
    12.071,
    12.067,
    12.086,
    12.111,
    12.286,
    12.125,
    12.078,
    11.9,
    11.743,
    11.725,
    11.22,
    11.06,
    11.0,
    11.2,
    11.2,
    11.333,
    11.42,
    11.267,
    11.186,
    11.175,
    11.283,
    11.3,
    11.58,
    11.38,
    11.383,
    11.4,
    11.417,
    11.36,
    10.889,
    10.555,
    10.511,
    10.92,
    11.05,
    10.975,
    11.88,
    12.08,
    12.26,
    12.25,
    12.22,
    12.02,
    11.7,
    11.36,
    10.68,
    10.06,
    9.86,
    9.72,
    9.683,
    9.58,
    9.98,
    9.7,
    8.6,
    8.833,
    8.84,
    9.0,
    8.917,
    9.014,
    8.338,
    7.88,
    6.9,
    6.24,
    5.85,
    5.34,
    5.017,
    4.567,
    4.417,
    4.343,
    4.267,
    4.22,
    4.213,
    4.086,
    3.68,
    3.589,
    3.629,
    3.55,
    3.533,
    3.55,
    3.612,
    3.556,
    3.65,
    4.088,
    4.086,
    4.1,
    4.143,
    4.3,
    4.34,
    4.257,
    4.16,
    4.083,
    4.16,
    4.257,
    4.357,
    4.322,
    4.186,
    4.263,
    4.229,
    4.133,
    4.244,
    4.35,
    4.529,
    5.367,
    6.083,
    6.8,
    7.117,
    7.1,
    7.144,
    7.1,
    7.0,
    6.92,
    6.88,
    6.883,
    7.02,
    6.96,
    6.917,
    6.86,
    6.65,
    6.967,
    7.08,
    7.32,
    7.02,
    7.088,
    7.1,
    6.956,
    7.01,
    7.045,
    7.429,
    7.842,
    8.363,
    9.183,
    9.717,
    9.938,
    10.94,
    11.28,
    11.283,
    10.986,
    10.78,
    10.767,
    10.857,
    11.46,
    12.0,
    12.26,
    12.0,
    11.4,
    10.033,
    8.95,
    8.843,
    8.3,
    7.575,
    7.562,
    7.578,
    7.96,
    8.455,
    9.129,
    9.113,
    9.488,
    9.738,
    9.911,
    10.06,
    10.136,
    11.1,
    11.06,
    11.32,
    11.94,
    12.56,
    12.633,
    12.787,
    12.829,
    12.756,
    12.817,
    13.44,
    13.533,
    13.533,
    13.8,
    13.886,
    13.85,
    13.64,
    13.5,
    13.28,
    13.688,
    14.08,
    14.34,
    14.26,
    14.2,
    14.087,
    13.82,
    13.74,
    13.8,
    13.883,
    13.92,
    13.512,
    13.45,
    13.525,
    13.9,
    13.98,
    13.667,
    13.525,
    13.471,
    13.52,
    13.86,
    13.98,
    14.033,
    14.071,
    14.36,
    14.4,
    13.65,
    13.14,
    12.933,
    11.95,
    11.9,
    11.838,
    11.75,
    11.425,
    11.542,
    11.844,
    11.92,
    12.433,
    12.96,
    13.083,
    13.4,
    13.55,
    13.48,
    13.333,
    13.013,
    12.471,
    11.929,
    11.33,
    10.957,
    10.837,
    10.52,
    9.4,
    8.72,
    8.12,
    8.017,
    7.32,
    7.35,
    7.917,
    8.327,
    8.614,
    8.789,
    8.9,
    9.1,
    9.33,
    9.26,
    9.162,
    9.625,
    9.789,
    10.257,
    10.286,
    10.287,
    10.322,
    10.233,
    9.9,
    9.589,
    9.4,
    9.325,
    8.6,
    8.418,
    8.464,
    8.567,
    8.175,
    8.133,
    8.318,
    8.4,
    8.525,
    8.743,
    8.6,
    8.613,
    8.45,
    8.408,
    8.67,
    8.827,
    8.7,
    8.6,
    8.636,
    8.655,
    8.611,
    8.425,
    8.378,
    8.36,
    8.31,
    8.27,
    8.127,
    8.4,
    8.65,
    8.789,
    8.867,
    8.938,
    9.114,
    9.311,
    9.786,
    9.817,
    9.778,
    9.775,
    10.17,
    10.6,
    10.889,
    11.011,
    11.15,
    11.183,
    11.257,
    11.271,
    11.233,
    11.217,
    11.286,
    11.275,
    11.271,
    11.311,
    11.367,
    11.371,
    11.387,
    11.271,
    11.2,
    11.1,
    10.82,
    10.317,
    9.927,
    9.714,
    9.586,
    9.512,
    9.511,
    9.527,
    9.857,
    9.917,
    10.014,
    10.086,
    10.12,
    9.862,
    9.683,
    9.625,
    9.175,
    9.03,
    8.98,
    8.967,
    8.875,
    8.678,
    8.65,
    8.72,
    8.778,
    8.825,
    8.887,
    9.322,
    9.388,
    9.06,
    8.88,
    8.75,
    8.643,
    8.588,
    8.14,
    8.12,
    7.86,
    7.65,
    7.6,
    7.314,
    6.9,
    6.8,
    6.811,
    6.94,
    7.033,
    6.971,
    6.929,
    6.96,
    7.167,
    7.2,
    6.743,
    6.733,
    6.8,
    6.863,
    6.886,
    6.867,
    6.886,
    6.867,
    6.86,
    6.88,
    7.033,
    7.18,
    7.217,
    7.333,
    7.322,
    7.387,
    7.39,
    7.378,
    7.492,
    7.657,
    7.589,
    7.56,
    7.72,
    7.667,
    7.86,
    8.05,
    8.05,
    8.08,
    8.067,
    8.113,
    8.113,
    8.15,
    8.155,
    8.2,
    8.186,
    7.825,
    7.55,
    7.486,
    6.983,
    6.789,
    6.225,
    5.74,
    4.72,
    4.5,
    4.16,
    3.988,
    3.943,
    3.96,
    3.967,
    3.9,
    3.763,
    3.538,
    3.261,
    3.047,
    2.871,
    2.729,
    2.614,
    2.678,
    2.76,
    2.867,
    3.343,
    3.273,
    3.243,
    3.09,
    2.992,
    3.025,
    3.056,
    2.9,
    2.783,
    2.733,
    2.825,
    2.9,
    2.943,
    2.967,
    2.943,
    2.933,
    2.978,
    2.871,
    2.875,
    2.875,
    2.76,
    2.856,
    2.925,
    2.9,
    2.94,
    3.017,
    3.1,
    3.2,
    3.067,
    2.983,
    3.022,
    3.15,
    3.386,
    3.467,
    3.443,
    3.625,
    3.738,
    3.914,
    4.3,
    4.111,
    3.971,
    4.02,
    4.12,
    4.1,
    3.888,
    3.867,
    3.864,
    3.783,
    3.643,
    3.691,
    3.75,
    3.817,
    3.95,
    4.186,
    4.383,
    4.34,
    4.343,
    4.288,
    4.182,
    4.355,
    4.7,
    4.717,
    0.141,
    0.1,
    3.7,
    4.114,
    4.162,
    4.36,
    4.5,
    4.657,
    5.06,
    5.3,
    5.86,
    6.14,
    6.129,
    6.183,
    6.233,
    6.24,
    6.32,
    6.383,
    6.6,
    6.82,
    6.9,
    7.32,
    7.513,
    7.8,
    7.87,
    8.113,
    8.833,
    9.62,
    10.029,
    10.86,
    11.05,
    11.68,
    12.68,
    13.2,
    13.66,
    14.1,
    14.72,
    15.0,
    15.36,
    15.767,
    16.2,
    16.42,
    16.66,
    16.75,
    17.08,
    17.28,
    17.4,
    17.52,
    17.68,
    17.82,
    17.92,
    17.98,
    17.82,
    17.6,
    17.117,
    16.8,
    16.567,
    16.457,
    15.84,
    15.32,
    14.42,
    14.25,
    12.88,
    12.48,
    11.963,
    11.02,
    10.583,
    10.343,
    9.08,
    8.16,
    7.667,
    7.083,
    6.683,
    6.42,
    6.02,
    5.44,
    5.27,
    5.4,
    5.611,
    5.775,
    6.425,
    6.61,
    6.922,
    7.533,
    7.7,
    7.71,
    7.175,
    7.0,
    6.5,
    6.383,
    6.286,
    5.42,
    5.2,
    5.0,
    4.84,
    4.757,
    5.014,
    5.067,
    4.857,
    4.83,
    4.66,
    4.933,
    5.025,
    5.1,
    5.1,
    5.35,
    5.525,
    5.967,
    6.157,
    6.156,
    6.45,
    6.8,
    7.767,
    7.917,
    8.0,
    9.238,
    9.554,
    9.78,
    9.917,
    10.213,
    11.2,
    11.25,
    11.517,
    11.96,
    12.05,
    12.8,
    12.76,
    12.28,
    13.32,
    13.96,
    13.988,
    14.043,
    13.683,
    13.8,
    13.862,
    14.083,
    14.76,
    14.92,
    15.183,
    15.28,
    14.6,
    14.186,
    12.82,
    11.983,
    9.58,
    8.92,
    7.68,
    7.287,
    7.08,
    7.083,
    7.125,
    7.26,
    7.175,
    6.911,
    6.243,
    6.0,
    5.983,
    5.875,
    5.64,
    5.471,
    5.356,
    4.942,
    4.55,
    4.267,
    3.933,
    4.043,
    3.975,
    3.667,
    3.8,
    3.9,
    3.983,
    3.982,
    3.918,
    3.946,
    3.86,
    4.18,
    4.5,
    4.575,
    4.575,
    4.611,
    4.58,
    4.583,
    4.589,
    4.52,
    4.41,
    4.362,
    4.42,
    4.556,
    4.757,
    5.211,
    6.0,
    6.4,
    6.82,
    6.589,
    6.411,
    6.778,
    7.17,
    7.227,
    7.85,
    8.444,
    8.715,
    8.908,
    8.95,
    8.967,
    9.15,
    9.3,
    9.53,
    9.886,
    10.3,
    10.475,
    10.033,
    9.157,
    8.371,
    7.3,
    6.836,
    6.483,
    6.457,
    6.42,
    6.138,
    6.01,
    5.783,
    5.725,
    5.4,
    5.24,
    5.217,
    5.217,
    5.3,
    5.5,
    5.783,
    6.26,
    7.037,
    7.475,
    7.77,
    9.0,
    9.08,
    9.786,
    9.92,
    10.012,
    10.067,
    10.213,
    10.244,
    10.22,
    10.233,
    10.2,
    10.12,
    10.1,
    10.413,
    10.643,
    10.856,
    10.91,
    11.52,
    11.9,
    12.24,
    12.267,
    12.5,
    12.6,
    12.7,
    12.829,
    13.08,
    13.08,
    13.08,
    13.0,
    12.525,
    11.69,
    10.591,
    10.071,
    9.417,
    9.363,
    9.314,
    9.05,
    8.971,
    8.813,
    7.25,
    7.05,
    6.18,
    6.014,
    6.125,
    6.267,
    6.286,
    6.318,
    6.345,
    7.033,
    7.238,
    7.567,
    7.956,
    8.314,
    8.35,
    8.7,
    9.25,
    9.429,
    9.75,
    9.817,
    9.878,
    10.02,
    9.95,
    9.2,
    8.85,
    8.16,
    8.083,
    7.483,
    7.429,
    7.26,
    7.24,
    7.66,
    8.08,
    8.575,
    8.87,
    9.5,
    9.2,
    8.817,
    7.78,
    8.1,
    8.85,
    8.95,
    9.2,
    9.2,
    9.175,
    9.2,
    9.3,
    9.486,
    9.614,
    10.0,
    10.017,
    9.95,
    9.84,
    9.5,
    9.433,
    9.133,
    9.175,
    9.156,
    9.15,
    9.188,
    9.262,
    9.3,
    9.82,
    9.92,
    9.933,
    10.0,
    10.183,
    11.133,
    11.85,
    12.3,
    12.243,
    11.117,
    10.39,
    9.783,
    9.38,
    9.286,
    8.7,
    8.433,
    8.4,
    7.975,
    7.857,
    7.756,
    7.808,
    7.8,
    7.767,
    7.657,
    7.846,
    8.009,
    8.15,
    8.12,
    8.033,
    7.929,
    7.483,
    7.362,
    7.469,
    7.689,
    7.683,
    7.95,
    8.57,
    9.475,
    10.38,
    10.82,
    10.933,
    11.2,
    11.62,
    11.74,
    11.86,
    12.043,
    12.6,
    13.014,
    12.94,
    12.717,
    12.686,
    11.56,
    11.2,
    10.1,
    9.729,
    9.54,
    9.557,
    9.512,
    9.18,
    9.3,
    10.25,
    10.171,
    9.7,
    9.757,
    9.82,
    9.771,
    9.371,
    9.55,
    8.98,
    8.929,
    9.23,
    9.571,
    10.28,
    10.383,
    10.7,
    10.929,
    11.88,
    12.18,
    12.183,
    12.2,
    12.3,
    12.314,
    12.42,
    11.843,
    11.537,
    10.65,
    10.5,
    10.475,
    10.32,
    10.425,
    10.5,
    10.514,
    10.456,
    10.283,
    10.256,
    10.138,
    9.783,
    9.857,
    9.837,
    9.783,
    9.729,
    9.52,
    9.28,
    9.157,
    9.167,
    9.225,
    9.567,
    9.612,
    9.66,
    9.98,
    10.14,
    10.183,
    10.44,
    10.583,
    11.58,
    11.76,
    11.883,
    12.113,
    12.68,
    13.32,
    13.36,
    13.313,
    13.32,
    13.34,
    13.217,
    13.44,
    13.5,
    13.64,
    13.933,
    14.02,
    14.08,
    14.04,
    14.08,
    14.08,
    14.133,
    14.18,
    14.183,
    14.167,
    14.3,
    14.343,
    14.5,
    14.58,
    14.7,
    14.76,
    14.783,
    14.85,
    14.86,
    14.817,
    14.54,
    14.167,
    13.986,
    13.44,
    13.014,
    11.98,
    11.583,
    11.18,
    10.967,
    10.083,
    10.129,
    9.883,
    9.6,
    9.223,
    8.875,
    8.856,
    8.72,
    8.62,
    8.375,
    8.375,
    8.133,
    7.914,
    7.5,
    7.37,
    6.72,
    6.127,
    5.871,
    5.767,
    5.814,
    5.829,
    5.914,
    5.917,
    5.957,
    6.167,
    6.5,
    7.34,
    7.571,
    8.02,
    8.167,
    9.0,
    9.622,
    9.857,
    9.925,
    10.329,
    10.15,
    9.375,
    9.238,
    9.171,
    9.138,
    9.1,
    9.067,
    9.2,
    9.3,
    9.337,
    9.183,
    9.183,
    9.417,
    9.567,
    9.709,
    9.279,
    8.813,
    8.543,
    8.587,
    8.68,
    8.7,
    8.771,
    9.017,
    8.964,
    8.95,
    8.99,
    9.04,
    9.125,
    9.178,
    9.2,
    9.16,
    9.157,
    9.238,
    9.214,
    8.833,
    8.709,
    8.6,
    8.614,
    8.6,
    8.28,
    7.88,
    7.733,
    7.471,
    6.517,
    5.28,
    5.3,
    5.3,
    4.38,
    4.15,
    4.1,
    3.583,
    2.212,
    2.311,
    1.517,
    3.0,
    3.06,
    3.386,
    3.76,
    4.143,
    4.35,
    4.209,
    4.425,
    4.7,
    4.75,
    4.786,
    4.72,
    4.8,
    5.388,
    5.692,
    6.154,
    6.483,
    6.75,
    6.845,
    6.912,
    6.767,
    7.017,
    6.989,
    6.638,
    6.18,
    6.186,
    6.32,
    6.383,
    7.217,
    7.5,
    7.5,
    6.783,
    6.417,
    6.357,
    5.88,
    5.833,
    5.58,
    5.517,
    5.34,
    5.42,
    5.68,
    5.789,
    5.8,
    5.25,
    5.275,
    5.614,
    5.912,
    6.633,
    7.067,
    7.467,
    7.933,
    8.517,
    8.789,
    8.4,
    7.833,
    7.757,
    7.917,
    8.125,
    8.2,
    8.25,
    8.433,
    8.383,
    8.329,
    8.543,
    8.7,
    8.813,
    9.46,
    9.567,
    9.933,
    10.029,
    9.88,
    9.375,
    9.333,
    9.357,
    9.371,
    9.469,
    9.622,
    10.125,
    10.157,
    9.66,
    9.7,
    9.762,
    10.211,
    10.29,
    10.55,
    10.457,
    9.82,
    9.817,
    9.786,
    9.767,
    9.8,
    10.056,
    10.2,
    10.243,
    10.163,
    9.686,
    9.54,
    9.15,
    8.833
  ],
  "watts": [
    0.00013500000000000003,
    0.00013500000000000003,
    0.00013500000000000003,
    0.00013500000000000003,
    1438.856260614,
    213.49243203600017,
    269.46899704199916,
    245.56759146094512,
    321.91624193070015,
    133.17694437273695,
    136.47539077114607,
    177.62552292461538,
    232.54365595036307,
    233.28579130219487,
    234.9787726797003,
    185.83699250830523,
    147.36281311230078,
    98.11214499800022,
    141.34608063799976,
    150.233203087,
    144.71577319799928,
    181.5817294199998,
    140.7834506760002,
    127.28202969844465,
    177.90358734234675,
    149.31981863549998,
    147.4973120235,
    160.66296937467996,
    199.2971383032148,
    121.54634021610012,
    138.32445521449463,
    189.86900912570013,
    179.77574412811498,
    216.22611594265996,
    158.43158175013588,
    94.91224185468,
    72.63729486276002,
    98.3503224127333,
    128.28906732456,
    217.3076047087199,
    215.6124718848153,
    171.69060808174498,
    133.0084077951149,
    132.28507456597487,
    203.45392649250027,
    125.565641685195,
    121.692910437075,
    136.45509149008922,
    118.79992537745996,
    119.62383393890192,
    170.78532400374007,
    197.7203868109051,
    197.2563058486634,
    190.2776074804034,
    140.74441604097478,
    110.83264889791468,
    48.2123391861,
    38.57293805399999,
    28.810325609444995,
    150.73821469708508,
    632.3767664678999,
    212.51380564296008,
    484.1299566274002,
    322.38203489999944,
    249.46073212891503,
    209.00095312015495,
    245.92184792518495,
    173.01135313909498,
    168.723360592395,
    163.05464014770004,
    162.120945590445,
    158.3496537687,
    151.05614171531997,
    133.32100741939496,
    124.52677003770005,
    120.42931605792002,
    119.38515664128003,
    118.05488458908,
    116.6469588738,
    174.69393444072,
    183.6395045942851,
    137.8455255760479,
    145.67044164821934,
    207.53432017020003,
    213.6953721836252,
    390.7638914354993,
    179.82023757191996,
    219.63346856712067,
    180.79543537264493,
    202.86490633364605,
    213.08479103407345,
    188.91420031291625,
    203.54153433417508,
    197.43306977621984,
    177.6174046400548,
    201.44037858100913,
    176.0970311621548,
    171.57700657691524,
    280.9756107600002,
    108.50721836304028,
    85.6931025126,
    92.89542134999984,
    101.012959404,
    158.53202241572575,
    193.54212801192003,
    598.4772505835546,
    160.98920850330046,
    254.994529780695,
    193.1173635177001,
    149.49682465008,
    144.6628327878,
    140.55453195444,
    202.43298893839577,
    191.9305388635053,
    234.9900931199245,
    811.5821941755006,
    404.0186841900006,
    315.65969649599924,
    209.93038035199967,
    213.1787115660001,
    184.1043184000001,
    137.18900247000005,
    123.630639512805,
    117.5456088423,
    206.12388066000025,
    289.27856088995935,
    184.4370987517056,
    169.23163149185788,
    163.71494835015326,
    199.8030166565081,
    276.713200783615,
    186.77798766402017,
    171.3092633115338,
    143.31785757600002,
    294.4927248770549,
    183.9620253206333,
    198.65606307800024,
    205.92578204934708,
    189.82832134677687,
    186.08550240650493,
    171.89109241901997,
    158.7014680602,
    160.34994552299997,
    165.7441599422801,
    192.58308194992517,
    182.23036029894004,
    198.89729123214556,
    176.3695183027777,
    173.6541944188889,
    177.2797527718049,
    154.32304503179995,
    163.5175307507336,
    230.35788617222045,
    161.78603542426288,
    143.15066282220042,
    195.24732958499985,
    152.64760071812512,
    175.78081409580517,
    153.15246809421507,
    153.08720308413405,
    212.7698505533251,
    175.28256932549994,
    193.24553450544,
    164.11748371559997,
    190.19016541499988,
    217.47867991307996,
    305.3095588454494,
    299.43694452570014,
    254.8933436669602,
    227.800304331595,
    181.8577559708252,
    189.24603451301667,
    172.1226583659448,
    178.86931375669985,
    237.36024173659635,
    320.58437525217835,
    254.84159470906351,
    246.3162120600001,
    213.1073685545543,
    165.407336090355,
    221.3401099142996,
    214.0525244279999,
    207.70156461804044,
    433.7792448695993,
    245.3184451284453,
    219.99498118469975,
    124.1296661079997,
    117.4656875705458,
    122.04035570672715,
    115.66423826584604,
    203.72545726215375,
    153.80801201955478,
    178.55328714220911,
    199.21261513866548,
    213.519205507124,
    182.9297346775436,
    158.95912378023155,
    223.0993588500012,
    141.6709494150005,
    112.00818358819512,
    97.07658362370002,
    100.51045446599991,
    203.85073447837075,
    357.40708776460485,
    227.73892639628508,
    590.7430499678994,
    231.28100396600016,
    233.72182514930523,
    226.6978181822995,
    318.0722536079992,
    249.20637247030555,
    231.67471641030048,
    251.38553060399977,
    233.68600018800052,
    272.7729506649599,
    295.674087161595,
    225.98773771578,
    216.9843705588,
    201.45309380161495,
    156.3378024501,
    143.06249241,
    142.51528134000003,
    516.3224739120001,
    470.2620864520551,
    615.3998901692992,
    402.8240587920011,
    584.20583667,
    295.010818212,
    347.55448700399995,
    390.45444901669526,
    445.6303042977002,
    444.8913654900001,
    338.4884929253335,
    392.000663238964,
    394.5977544267545,
    378.91335844800005,
    323.55639276408556,
    260.5318421313001,
    203.93079842904783,
    214.03790556269985,
    177.44188195317088,
    194.8306267336885,
    345.08810623358386,
    316.9780186201366,
    264.0610833489599,
    300.5778374140664,
    297.70012298399956,
    271.11925458785475,
    224.6589920071048,
    139.38414301322308,
    145.80670261831605,
    197.27331423390552,
    145.4929544597411,
    155.73519423130497,
    144.0558206053261,
    129.68072080918503,
    156.70546619821343,
    185.92200280450504,
    174.57920959230006,
    161.3756004884399,
    175.63185888268492,
    196.3873089498999,
    212.45086561904463,
    253.6831145187599,
    175.97604192540038,
    195.36869822200035,
    195.2655511726449,
    181.4619387981452,
    170.13310374269997,
    151.71345430180477,
    144.74510631975716,
    178.0969516626183,
    210.2655205996999,
    204.3111780576122,
    166.13575683989998,
    154.94847198100064,
    123.16256199599944,
    88.44385467899971,
    54.725066297999504,
    31.924605047999997,
    128.89783900800006,
    126.17215835399996,
    240.5613639820001,
    276.24955243305845,
    283.3412036005551,
    174.749618394675,
    209.45598052050008,
    297.013977901305,
    236.6597704323005,
    231.71486995418155,
    203.84656159963637,
    188.34188934288497,
    175.9396235965665,
    107.88495885399124,
    128.73039365329964,
    176.90903539680497,
    160.70568149560484,
    115.12580428230017,
    123.6529054725004,
    124.30459384299982,
    134.23350586299992,
    70.21987115044492,
    92.53780316461956,
    184.66396546770025,
    105.79876940737492,
    137.6068133491151,
    190.34332762062647,
    158.98453227523595,
    165.31527761206831,
    167.49457873980003,
    349.3083825510001,
    133.69676433846575,
    119.8009097522002,
    110.99452140282696,
    102.31301455039498,
    113.29766092170036,
    137.18518238314508,
    191.95619343269968,
    158.35174738200058,
    114.60673658303998,
    110.8668001266,
    137.49603566719458,
    133.76454121170082,
    314.31428998199954,
    235.59557907504,
    237.93461395298547,
    184.71621295525463,
    176.90389240830024,
    212.57267570200017,
    346.282368867,
    218.02088652600003,
    271.2541914068847,
    196.76188432589996,
    187.01370767869503,
    186.0509777757,
    198.9326861879996,
    211.6656511930904,
    247.92173810399953,
    291.5884887072915,
    306.124814614167,
    292.25120112566697,
    279.21345277466696,
    269.8634894219998,
    253.43751950530472,
    237.8592426323,
    195.569732147445,
    144.51411136770014,
    80.271635946,
    122.71614390600035,
    137.50727477999982,
    151.47967595099988,
    157.45829915400023,
    204.4224024479998,
    198.20185046999995,
    208.6955962680007,
    150.3464427940001,
    200.07872521028585,
    288.2237051011386,
    289.5580044764002,
    288.0968073919198,
    214.86291007620048,
    342.79063296205436,
    203.984078818995,
    244.5321126897006,
    223.9867102319998,
    240.5480611623753,
    286.5386981789551,
    303.04162787729945,
    305.97303778579504,
    313.5081163250848,
    250.90827276844507,
    256.30986468566,
    252.22550828436005,
    244.12146149939997,
    243.471584178195,
    212.732749843845,
    196.001104069755,
    214.08823282510525,
    259.0316610842998,
    202.793076184305,
    198.91717609326005,
    188.63470878220505,
    159.81380347229998,
    149.50493408830502,
    213.17820232229963,
    652.7181609479995,
    592.0598746696951,
    918.2269000377004,
    662.8242788099988,
    492.1301469613058,
    558.8561167974431,
    1131.9959315427018,
    938.961622031998,
    694.5521000641968,
    1109.590140137699,
    852.095306178001,
    853.0788796379993,
    770.2258435480003,
    604.325939182695,
    596.252007803055,
    565.8895954473,
    556.113407992305,
    627.5933944133523,
    653.6935586138998,
    719.4039452906668,
    932.3437839769604,
    870.0429257877747,
    780.8110902465005,
    592.5576256190552,
    682.9451027642999,
    519.3336895401817,
    510.23519092199984,
    482.777340967636,
    326.2566033687274,
    353.71435703999975,
    282.3589642859999,
    284.92317288300023,
    303.6845161258047,
    284.23282263139123,
    225.23960992735488,
    177.18773490329977,
    144.02120722500024,
    200.9207775679998,
    175.17074089594863,
    179.88884875252117,
    202.7701530073333,
    201.67134813150005,
    223.11188916430805,
    228.23536003440665,
    243.35380578659965,
    152.29873141687497,
    150.22070493583328,
    213.66398490129816,
    191.62848635270691,
    189.36322552583997,
    189.52012852068,
    126.55787335877628,
    110.80616101188362,
    102.99937113052668,
    119.966564512246,
    127.85990380472722,
    103.42035236714548,
    142.75952016581192,
    145.77828604450508,
    201.16746181829984,
    187.64974390800012,
    93.44864857369498,
    232.3040654876997,
    182.5244670720001,
    167.39669801400004,
    151.270913729505,
    191.14330878349483,
    189.7656629691286,
    228.3936941305794,
    225.20206064580017,
    168.30915599249988,
    151.92871591955517,
    162.9560038481838,
    209.1921728219167,
    259.64646654710486,
    297.63099759365156,
    286.6076794825952,
    267.97530553060983,
    265.4646107579998,
    300.6846308926161,
    209.32414139352605,
    173.55640063891963,
    133.49443943507342,
    101.0168669088,
    159.87670024904014,
    392.74426776289465,
    369.49031295439494,
    274.98781511170023,
    335.71102977337443,
    267.4055329185001,
    428.42497693500144,
    278.203250305305,
    274.6924597376336,
    261.0550373339997,
    274.447601794667,
    266.0404280699996,
    248.84270911073463,
    200.07369664320373,
    201.15000614446345,
    187.1878661562631,
    187.25090844654125,
    226.89155129458533,
    241.77981889638025,
    236.87307580761887,
    245.82889935600076,
    223.48425190888497,
    219.34494673256697,
    239.6719577610003,
    211.966046049,
    181.4568024659995,
    206.5018348979992,
    205.3540334999992,
    196.87838101963632,
    189.67065118200065,
    169.86930321504056,
    201.7372441136554,
    227.66260288079968,
    203.517095091,
    207.63678654391433,
    230.41841278329136,
    174.2334320436069,
    146.30276321755525,
    149.04372668130063,
    110.96325719933212,
    138.58423790666637,
    126.91749330730528,
    112.1050291282194,
    204.58202010420015,
    106.22400766200025,
    132.34620259169455,
    175.2984569884058,
    164.1365640648553,
    188.58192724309453,
    208.50637841847873,
    133.90467235755213,
    182.12936984080224,
    240.76238128350047,
    207.8901359159997,
    234.3355027240003,
    203.91012456306044,
    189.6104055032997,
    202.51746153000005,
    230.18914148855976,
    194.51732044506727,
    151.11306442200012,
    163.44876539999998,
    154.56011854104486,
    191.64241439023155,
    363.8347611852753,
    201.80748447865423,
    210.131657745,
    276.42213943201125,
    260.1558406187556,
    245.79808767125937,
    190.61191309426732,
    137.79324895884724,
    102.8441657223,
    141.95674124699994,
    228.36829720500015,
    426.6849308579999,
    397.884421193555,
    418.9519800728549,
    315.0788165694951,
    290.9358036747001,
    365.6969386139996,
    330.81310510200024,
    342.9585549905545,
    455.8614161053001,
    388.563982214355,
    346.1401464863402,
    304.4870493246,
    290.91769660104006,
    267.94804663260004,
    262.60854059999997,
    411.39880412399975,
    391.54921830461535,
    297.14474999989505,
    281.922583347585,
    271.22045352990006,
    319.2903374078848,
    281.23789983520504,
    303.7266891732602,
    298.01431180948526,
    334.5673524528598,
    285.172765937775,
    282.00575739522,
    271.2332217882,
    261.736170996645,
    260.413227891075,
    232.53568615050008,
    223.28090929200005,
    219.923254014,
    333.3888991799996,
    230.52370655999997,
    376.9590224776959,
    265.57709084069995,
    234.471422257305,
    229.91002440126,
    229.18532201152505,
    291.2695299954443,
    253.83518181270136,
    400.3156663919997,
    240.837496944,
    243.8109895044432,
    259.5754341927013,
    266.2605533360541,
    239.4565550313,
    214.88314741291495,
    197.862727306725,
    195.19621481758497,
    622.4694511839006,
    355.02914506800084,
    218.63706998812495,
    1229.8352515695017,
    504.5086972439992,
    496.8969669059997,
    292.873003794,
    290.981244423,
    278.662999536,
    259.483910268,
    239.972757474,
    204.656941596,
    175.27513446600005,
    165.74382460799998,
    159.68919898200002,
    157.955967993945,
    153.8308409247,
    533.6857806840004,
    159.107901192,
    119.24743526999998,
    260.7303302661043,
    222.44956967369973,
    295.8742166293338,
    280.40156235105496,
    381.8344209443401,
    322.71131680252086,
    255.24148191419985,
    299.312592882,
    259.4396457726666,
    206.6102850414544,
    238.5718664510001,
    185.77086356155525,
    232.28809270510507,
    187.62402552085484,
    180.94035579844473,
    192.50242226571095,
    155.22866849240503,
    198.7606510432952,
    167.66421462066018,
    193.16348655206625,
    166.43622949774826,
    159.10576651471465,
    142.52524050068843,
    144.27558499669516,
    165.6757611053472,
    142.1175157630804,
    181.28173382069275,
    149.45969102639998,
    180.4587368978764,
    167.93731904662133,
    163.62400346340038,
    181.3318362322276,
    171.1186419376092,
    161.74553518933303,
    159.8586021793543,
    134.5139575472998,
    182.30781153794464,
    195.85741187670035,
    158.7630821123551,
    186.39094834703715,
    140.73215772857998,
    131.0232364865496,
    148.87048889344535,
    135.14243098831523,
    138.785716593795,
    119.31972610395812,
    96.85743187403476,
    91.37242515011503,
    142.27703955390524,
    158.00910391361302,
    200.49350368269975,
    370.3963945700551,
    152.42332760729926,
    169.57667764644046,
    154.10118097860033,
    137.16809529,
    120.79376019466666,
    160.33774493999965,
    173.64796107694409,
    211.02785460070015,
    226.05889972200023,
    211.85901485172224,
    214.63460393130077,
    216.346562894,
    271.1738316808055,
    222.68646481968435,
    373.2152632707688,
    174.1951075593333,
    212.64187582391995,
    212.2762328313175,
    162.27780472656028,
    155.0431319369215,
    136.2492826397083,
    124.82665406011505,
    141.83851162777992,
    304.8160831143449,
    303.803006198145,
    392.9870480597553,
    269.3482850452201,
    539.0991692381997,
    409.93783543799987,
    238.21655436994507,
    219.61928053566,
    208.8200716854,
    207.80950791880497,
    302.7074044526548,
    556.7689106073009,
    472.4321056739998,
    451.077174579,
    420.0340180065,
    461.5753314599997,
    482.2053404519224,
    301.6529820976998,
    303.1459475644783,
    290.8643995767004,
    228.23829180312455,
    227.8572540462468,
    213.043471250085,
    252.394736402676,
    284.76193862185255,
    318.48170409761485,
    135.442783925895,
    195.57289382647713,
    383.23576370112,
    325.3343664272851,
    312.2415235899009,
    248.79416161895875,
    1175.2903686084005,
    223.06202486400005,
    371.936261502,
    607.5182651339994,
    547.6209082100004,
    346.63699054019446,
    365.02732019740546,
    356.7827370669149,
    326.87390001066,
    367.160060132955,
    629.1860612232997,
    422.673682012695,
    383.961737944395,
    574.3225513377009,
    467.32260992495907,
    409.25160683339993,
    392.734507821,
    381.654986466,
    365.023047702,
    523.3211314699204,
    933.6317177591992,
    535.8285367379999,
    443.6319201,
    438.455970174,
    428.985596918205,
    407.2379184483,
    400.452576204,
    481.86029622600074,
    518.5672924149429,
    430.7845373107004,
    383.0741277940801,
    377.6533972728,
    430.2403771743757,
    651.6944957325001,
    523.4224156920002,
    395.05936378930505,
    383.598536931675,
    379.25639377738503,
    444.3606115478993,
    517.5991418819999,
    574.9830542160014,
    493.2005036611938,
    477.02711182558534,
    642.6521204138999,
    518.7946792440006,
    443.6187076892305,
    376.6060706380588,
    339.59089307569496,
    275.7636433077,
    270.999745065,
    267.25811981591994,
    262.0270230222,
    243.59922789187505,
    270.2939060641798,
    376.4266333872398,
    355.97382377160056,
    594.339806085195,
    547.6061048617005,
    498.7686142629442,
    503.2542297227002,
    447.6714175800002,
    379.9803033270001,
    368.883901999695,
    371.5994212489949,
    348.8588827129182,
    310.1509693020151,
    264.8295952520999,
    259.6937060427641,
    257.1689479427551,
    241.7309806533001,
    194.06457754800013,
    133.96418373300017,
    123.26114734266658,
    114.19636797855492,
    91.0589199486333,
    105.79507944799973,
    220.34220710060055,
    172.86493964540398,
    177.79064272340906,
    219.7428428850145,
    157.24546117410003,
    173.67934241428557,
    212.61046586200015,
    141.10192073099998,
    137.42805110808004,
    212.42519570681773,
    236.0709762459149,
    269.49114411745495,
    198.2397397302599,
    185.44284148060623,
    219.5981513155784,
    217.22878928230273,
    216.82238567693076,
    209.29901961241495,
    228.36712748357365,
    253.06356737437488,
    257.53766143249993,
    223.8204100149047,
    223.60411318438307,
    223.3805345447895,
    154.45498904542507,
    141.4578887311949,
    154.19232262429904,
    195.7142805412597,
    170.10503320437482,
    185.7485468908116,
    143.55950195669973,
    164.552564983295,
    149.73225072192224,
    165.71459325732,
    214.9245452832002,
    186.62969576244268,
    159.4531957078385,
    169.5387383700001,
    171.20370557495977,
    191.72152374235625,
    199.7729550380849,
    172.60711098777494,
    196.89618756122,
    194.90986187969995,
    167.1584801580002,
    167.40101500699996,
    135.97378727784726,
    163.92439799847395,
    209.7016831751724,
    157.97415414789765,
    143.50875880540528,
    140.64749339275974,
    156.2352214043829,
    226.97295000868468,
    245.7117809328599,
    191.73762295495555,
    161.94912621402,
    161.75638702132505,
    251.65108172549992,
    337.1044564129999,
    261.6268671189149,
    261.58390234468493,
    256.20644956590024,
    263.80914042844444,
    246.37655290105496,
    249.05285277718625,
    232.39485655309505,
    231.47987437225504,
    259.1812501842597,
    234.65318845402504,
    234.4199574413851,
    250.55174916198473,
    249.4843084797052,
    244.19015843668456,
    257.76836434660504,
    234.6242495741851,
    243.68204817990016,
    262.61605355181837,
    278.4006028758262,
    254.36137105427724,
    242.6538615901509,
    223.0157861484702,
    194.6556399808932,
    173.82071223947997,
    169.08717742588522,
    170.70371273690515,
    224.137550951655,
    222.90428891935545,
    186.9058028743399,
    242.4709813575609,
    195.02375863139977,
    187.39493639313875,
    213.949442067078,
    253.309679074575,
    242.7908003606251,
    230.3252884095,
    191.412491489,
    175.67331229780524,
    154.27608432292507,
    150.64314574221984,
    137.2212547782,
    138.39315993299985,
    154.42365756471978,
    131.3054439100748,
    152.59357278670552,
    195.19204002129408,
    203.24867877372063,
    134.04628389120003,
    127.25387670600004,
    137.79753117200022,
    171.00283800214578,
    187.8733638759536,
    202.81808552138205,
    218.0112047285453,
    185.90428822199965,
    153.10769713517664,
    178.28016772499998,
    171.2255604710403,
    155.39729749659992,
    152.5593475299999,
    175.7790286929184,
    180.61270093371823,
    183.79416927019523,
    139.67707244008477,
    174.4950408270151,
    162.4619234035734,
    167.85408843023353,
    196.59811686452267,
    165.62433759164503,
    167.51177577508747,
    176.80596696009133,
    175.84932177204473,
    158.24583395119808,
    143.42111655834125,
    131.06252954635113,
    101.96573246743274,
    91.42091133630032,
    81.57693454418184,
    105.3354820561951,
    124.4712585296998,
    101.77693953655492,
    105.93337722499513,
    79.72480205298001,
    103.47616980850482,
    92.60178891963317,
    106.49000028305332,
    133.26035177072188,
    204.9826187711549,
    149.95381688186876,
    134.24662886398227,
    195.1096660178827,
    128.81019831280474,
    147.50127975630005,
    192.52743020399996,
    99.79111096500004,
    123.13747031699953,
    100.323948787305,
    106.54758910738066,
    101.687349090495,
    116.73591347970032,
    106.74777787762424,
    112.82251287449998,
    103.94274838895998,
    106.04740229027476,
    126.04517264999974,
    150.9423543079601,
    181.80265755784524,
    163.6319042077816,
    190.06577870097516,
    177.6440467485,
    136.63731345399975,
    171.6223780305,
    153.19756751400007,
    165.92760852042,
    176.64542847034514,
    167.38407029319998,
    148.11329160753226,
    129.2840643267827,
    147.6768164175449,
    159.13882918462002,
    141.7256606415348,
    167.32811271630496,
    167.89248782368475,
    180.16173811601465,
    177.97866147877633,
    111.3219231913202,
    173.33535342220063,
    217.7659506653054,
    171.9368145118542,
    185.1738495547718,
    194.92823346914935,
    212.33859691848917,
    153.33651451667987,
    178.4787770116751,
    167.02786883705988,
    170.5024987764004,
    162.8468961654453,
    180.8206177476055,
    198.14619153781015,
    167.94311728191158,
    214.5044803906443,
    178.96098174712017,
    172.30441361294464,
    169.70385729757177,
    172.37331467592017,
    157.18070084008485,
    174.64516573052512,
    158.7901521963068,
    166.50168682786375,
    199.34890325729697,
    159.50236410744148,
    181.12091244249984,
    201.26898733600035,
    176.9221103115555,
    199.75251390480048,
    147.0983033033332,
    162.2622548236379,
    151.421576216745,
    163.1711508438843,
    188.6671792247412,
    131.66084491172455,
    131.35400918170447,
    152.23436947956264,
    138.2704315896275,
    141.9231769385941,
    231.6124198445737,
    202.41718459660063,
    178.62451245358514,
    191.5679422763623,
    126.69726044789957,
    189.1372736459996,
    167.61510331800017,
    159.3075458719196,
    133.4208264001718,
    118.45663261910454,
    150.0127007643975,
    140.07469062642392,
    148.83951585468523,
    174.90190410579473,
    175.40681730655547,
    194.09930935229983,
    188.6244067380776,
    201.3656725558455,
    139.86342191869974,
    183.4850672196454,
    195.7619516266196,
    202.36230286791513,
    105.88784759321236,
    157.88628487949978,
    78.82967380229891,
    54.46247219503488,
    48.15922582280006,
    291.36664502489975,
    192.3578343650397,
    147.5312906206815,
    232.87813002179809,
    195.58365593400143,
    188.39014588135535,
    342.70824409229914,
    286.34901561733454,
    281.19387686400006,
    263.91487033090846,
    185.19665449244803,
    171.1609872618784,
    172.373687705894,
    139.41382236870064,
    151.28512747733365,
    161.82097261089913,
    173.59683432270054,
    187.16624094049996,
    134.3882723206316,
    153.30529239799986,
    234.79627272179437,
    132.8679253497,
    104.58868762800005,
    161.44407762379487,
    313.06508095489517,
    491.4947459456996,
    358.8656636406153,
    1018.1958478640996,
    415.68590285400137,
    922.446549056999,
    886.030851204,
    983.4801549719996,
    967.6299770940012,
    997.0396993439994,
    898.5923599380008,
    896.7897766679991,
    1052.827778843999,
    880.4764608958051,
    1275.9048290822998,
    990.861357558004,
    1053.7622406119976,
    835.1838759539997,
    1253.491251446997,
    1078.792255404005,
    967.9552396919958,
    984.5480546280016,
    1072.1657712000003,
    1059.794118630001,
    1008.2510656860028,
    950.342439629998,
    829.2363297000002,
    800.5971469980003,
    740.3688190400552,
    701.9861795373001,
    674.717056337805,
    661.944981044655,
    595.4474547993,
    542.248493484,
    459.03664728600006,
    442.936622298,
    392.6644108170009,
    416.4498483403634,
    503.718352948545,
    465.7936431526991,
    484.425236189445,
    481.4158340230123,
    440.4972158286999,
    405.7631816159997,
    403.85165569463777,
    338.34828344791106,
    284.2888408536455,
    199.46543838070068,
    178.0889971160002,
    207.6689127140005,
    180.24277081309057,
    158.9848618479997,
    222.44119316813024,
    106.1132921590248,
    153.6964750893752,
    112.94876718736975,
    147.33828803785858,
    161.46837139099483,
    257.87038534769965,
    188.34829511400025,
    200.79014214712535,
    202.4490730575,
    186.06502542272725,
    175.8667612074448,
    252.07305090965997,
    230.95069314390065,
    225.55713898326343,
    238.1509430466666,
    195.39142346933275,
    262.72456395773713,
    272.26072355563434,
    246.81557456690447,
    145.49941869810965,
    200.08443719529984,
    199.69480739099947,
    206.5704594536951,
    252.0258391845751,
    244.58131418942276,
    225.9322779184617,
    240.3172402299998,
    190.21444908437533,
    225.34203673646283,
    100.38105671448837,
    58.29644034586036,
    87.94195703640005,
    282.26055892499977,
    220.82806192180507,
    204.9949779083546,
    159.58485683730015,
    279.63647486249135,
    198.02954249244013,
    212.34576344459975,
    230.3342473280552,
    319.06407183259466,
    556.3101626396999,
    285.36267528000076,
    389.08970528305474,
    434.9827021613006,
    380.4851428439999,
    1195.0865869650002,
    327.091980924,
    295.66747149599996,
    675.2403043200004,
    1228.8863899920009,
    432.5958715279194,
    442.9157335323448,
    396.4152592926451,
    554.4409876227012,
    489.7992394180792,
    571.628785241745,
    1394.7058115666994,
    723.3304260720001,
    775.3277415714452,
    756.2695056047003,
    748.2461175720002,
    791.3155836039609,
    683.3117117013996,
    480.2023177741117,
    348.0299695447,
    334.76269277999916,
    265.5445780418177,
    223.94050403420545,
    174.43878076229947,
    136.58254562094592,
    212.39414632207527,
    251.8039541988524,
    247.19885241712495,
    246.57810663758448,
    206.08113028231747,
    188.2944512667,
    141.97212077944567,
    172.77856713832534,
    153.79723934349997,
    170.73223500310712,
    215.8792423099985,
    182.4045250637724,
    197.2336513798002,
    192.8799979040113,
    133.91527165699517,
    159.07111495416044,
    149.77336742149168,
    177.66594932147137,
    144.48060166691528,
    193.58160108652208,
    201.324711228392,
    182.65556675117983,
    154.26534828865306,
    131.98915284395963,
    143.6050736014,
    160.8358844960004,
    166.8827652920004,
    166.6993287997917,
    120.81905990062484,
    139.43693368187456,
    125.49636851789973,
    143.96681520844498,
    149.37505915098458,
    168.28459825473115,
    126.99951606939128,
    138.23324013055813,
    179.87280661761844,
    143.2980027173427,
    144.52483612225507,
    174.63097349856957,
    154.67269363589998,
    149.2877888757894,
    200.37397949799976,
    63.07673424541501,
    59.28471031168499,
    98.24871570119144,
    159.9509594362001,
    115.37738657050528,
    311.19202446629976,
    175.29367050615446,
    156.69535391022484,
    150.1666332315342,
    164.23417058519982,
    144.18105719080606,
    158.48809628515716,
    160.6257829478572,
    218.3211937219996,
    246.20405024195992,
    262.05829106340036,
    264.6126110506245,
    264.950109046695,
    308.03387615155526,
    320.9251328726847,
    295.6943537304882,
    262.7145809259603,
    176.60092835034447,
    193.70919149505517,
    217.29357504129965,
    213.72815584991983,
    205.36755683370012,
    188.5683598685361,
    160.32478406707497,
    121.35166488750032,
    117.00426885599926,
    114.24435106055498,
    90.31620071185574,
    125.47307507729911,
    157.8005310200003,
    120.92911439044512,
    188.64419789669984,
    151.36858136245502,
    230.6388655709249,
    195.69723974549996,
    368.7941363130001,
    201.29898427200004,
    264.15474990895996,
    198.42734353140008,
    193.16056092408013,
    200.0325792181049,
    203.7498373675948,
    192.2689932791402,
    181.4345486016,
    188.147024076195,
    180.5336259777,
    176.98298308799997,
    175.972661118,
    239.60269320429512,
    426.35269885684545,
    318.4036478352596,
    269.6669502504003,
    883.5313117469994,
    408.1592091980003,
    482.41755300599993,
    324.6706849603041,
    398.2938174023002,
    432.5490861899996,
    440.32483856999954,
    408.1778751066158,
    651.7602306620993,
    349.821170424,
    349.821170424,
    344.16588235200004,
    320.93579879437516,
    268.1239545666819,
    223.81978285348495,
    209.18489453262725,
    221.24660659345517,
    254.5075973268448,
    300.67732863119386,
    259.8404706989075,
    358.342298627385,
    284.44894519219457,
    256.63432409970017,
    225.39115704499997,
    212.34194750699945,
    201.4385051090407,
    138.6552820509747,
    218.72480981347155,
    106.6060181292598,
    91.74481306091968,
    96.28151135407516,
    124.86356481469504,
    104.42900781162002,
    142.12158412000497,
    152.45786303886004,
    242.6829358874399,
    136.88597502659968,
    258.74210914499986,
    216.09950923000008,
    302.71567493461527,
    217.3642880301,
    224.37522162655517,
    192.9561411242013,
    329.0013993161999,
    298.6137387680002,
    330.74795345318154,
    272.4226249200003,
    258.71914847515404,
    231.20993891794495,
    176.1615243096448,
    191.99317222231485,
    177.25399553409977,
    134.682650415,
    206.31284541705912,
    253.625845926,
    179.3929680851249,
    185.85742450049997,
    418.3277578530003,
    139.23237002999997,
    125.396597886555,
    93.84651894930002,
    337.00464097199955,
    242.71948233,
    212.02170244499968,
    173.39477473499997,
    138.68515895999997,
    137.78490467812503,
    141.69112053749978,
    185.34537765000064,
    181.99704124296,
    211.64337440844008,
    258.78958125659983,
    180.11313699055472,
    169.40565290729998,
    164.72081729099995,
    151.022498646,
    147.848412702195,
    136.70792809639497,
    149.58120220582546,
    137.05821765006004,
    136.80903761640002,
    143.56179558292004,
    172.65925112327997,
    175.24502193780023,
    278.2964182079999,
    259.5833392859997,
    180.5183829226949,
    186.88384290270005,
    265.23611379844493,
    460.5715326613948,
    458.1289123227001,
    547.9369111350006,
    364.1666053791456,
    319.29113269675474,
    291.9839580066334,
    231.59851111144505,
    237.57050983470015,
    233.34785233895985,
    194.66650868339968,
    203.41485323719556,
    163.52012129559446,
    143.94354962812534,
    135.81283628376409,
    111.73222031052624,
    112.61451978399256,
    100.82516475338194,
    96.2097033718054,
    97.42501016865512,
    119.19961528256016,
    154.42574832320904,
    165.23201589209975,
    124.75483089299976,
    136.9962621395481,
    175.71719369372803,
    219.4988963226968,
    208.62721464078,
    212.91250299211492,
    318.70297790265107,
    89.263739160045,
    135.16555428270007,
    210.35948664300005,
    400.8752296886248,
    604.9724991195006,
    354.2612369599999,
    330.4010360776945,
    504.8289502076994,
    401.99549833799995,
    391.4012652240011,
    399.9453563999991,
    381.09800014414486,
    634.1335120767003,
    442.8941662670399,
    339.8482785426,
    324.442988528055,
    404.86497600807814,
    372.0381459912464,
    367.9831273439996,
    275.22458897000047,
    267.78436513640906,
    243.56305166609997,
    222.57579315785577,
    196.56827641937983,
    161.3341443047998,
    183.68472345046143,
    475.42832326999945,
    193.32431169030824,
    165.5364152399005,
    178.07625681085509,
    192.22501382130028,
    161.67097174438504,
    146.00996453428505,
    309.5843688099003,
    131.559760677,
    128.770847969115,
    190.10978781210005,
    301.7129533223847,
    401.0220045218998,
    287.7686879694447,
    514.6109364627001,
    330.8383516971155,
    604.1718728721003,
    455.6406791339994,
    291.9537933804451,
    296.03989223269974,
    333.8809490500006,
    312.99639430103923,
    425.67132056459985,
    268.499639009145,
    249.95225692765507,
    203.54310607530005,
    194.857755435,
    193.42492343062497,
    186.30999101550003,
    207.67528384987511,
    267.4232846324993,
    197.51565677703988,
    192.57299513315996,
    184.617621519345,
    183.09957961326,
    177.86589152832,
    162.737470062645,
    187.64208839805497,
    164.428102507755,
    162.18843495574498,
    159.909857203815,
    151.5890763681,
    142.18102524,
    137.285521365855,
    141.6797013181049,
    164.3314895241749,
    195.1819116338765,
    195.00307891037997,
    178.35326509680004,
    316.1373036360002,
    327.14217286800016,
    220.25369821444428,
    437.6878543286996,
    338.15396766244567,
    506.9309723097,
    457.4900910059997,
    404.8747152489442,
    412.0206115834952,
    974.1305006817,
    559.9059190800001,
    420.21394705199896,
    367.190767698795,
    376.2895759376996,
    393.90286379399953,
    360.13781601055507,
    514.5748362332994,
    456.45277908600065,
    568.7774949060007,
    603.2752907206946,
    536.1010340456996,
    467.2816940100003,
    424.9161982679999,
    480.4218747480012,
    428.191636224,
    502.0906457956937,
    467.4958828197004,
    440.8490470704452,
    435.56666550250503,
    534.7198841823006,
    479.2215857436445,
    569.4592320567001,
    579.6347211720001,
    563.9296054319994,
    528.9358808340003,
    505.82120258944474,
    542.3049730827,
    510.9934858589997,
    493.28368641055505,
    468.5280809133,
    436.21784667580505,
    420.6819017952601,
    377.7676398594,
    345.80733446304,
    277.7055211986001,
    261.0667297516268,
    255.04481172924537,
    239.5162064831897,
    191.18574570203452,
    213.9766611758147,
    192.87702067504503,
    182.33762442269995,
    167.607674365245,
    192.526659269325,
    168.66911888605995,
    199.74468703439996,
    174.55511512599992,
    165.81641777786416,
    182.056822840625,
    179.5377447954055,
    174.35808730674,
    154.5559497766,
    172.367873358,
    178.59791744645457,
    164.68676143100498,
    167.006505678185,
    156.56343005170493,
    162.28525072583997,
    126.68299722821484,
    115.6683306041399,
    74.69240789265515,
    54.613284487155,
    172.16874240310497,
    125.56017091230004,
    348.92520273599996,
    165.86742157138497,
    423.5949498878998,
    213.71155291780516,
    351.37996196230006,
    243.99695498128,
    377.6781109571544,
    230.61900625267631,
    249.12700094661503,
    178.52103230010002,
    146.85089273812503,
    140.38167617142,
    137.710608765585,
    136.40815177182,
    134.9988699822,
    133.76661637030503,
    154.58145655229987,
    154.6221633642859,
    175.94894503195417,
    138.32237313874498,
    138.041471456145,
    187.142705826255,
    185.9427372901051,
    176.89704206988637,
    142.489069983465,
    135.0077140179213,
    127.98971510234496,
    140.32861402740514,
    144.6722499723,
    125.98746632199986,
    180.64043641138625,
    172.1150938454548,
    130.03674512034002,
    129.45964265159998,
    147.49473635100037,
    174.54017594699908,
    145.9632095853751,
    160.3097586772204,
    144.91192814819954,
    137.24698244400005,
    137.066636937855,
    151.53149737721995,
    139.26064834524,
    125.95598558179502,
    125.97143295697812,
    122.80462911386468,
    156.95498758888706,
    208.4683761966,
    210.026398017,
    196.8678423573333,
    182.108299867695,
    175.22952202258497,
    203.82896177204583,
    158.64940182930002,
    211.231410402,
    229.43702989000005,
    169.31094368123075,
    219.77187638199996,
    252.357251925,
    225.42797785144495,
    154.53430758527998,
    139.04016517738495,
    141.21641173395494,
    208.30254727141764,
    167.10625703715786,
    220.89909967896,
    212.11921969739996,
    215.54866539364505,
    195.27181526670003,
    148.80073825651493,
    185.1078883363279,
    225.80617796249993,
    174.00093182999976,
    123.35179832019531,
    108.3366449356106,
    135.1192106358261,
    160.17240822422772,
    148.16230064563,
    168.04863822545377,
    169.43479541787835,
    159.6010773058169,
    139.56667793237497,
    137.98992651273787,
    152.91939324293827,
    220.14765054535513,
    179.93669961421492,
    161.62433445602005,
    146.4462693042001,
    91.31554698326777,
    98.06553065140012,
    130.95974223211147,
    219.43824046936024,
    175.30567634301426,
    192.61586943749992,
    209.13177779453585,
    242.15317643125496,
    251.7850714601549,
    284.28492826530004,
    203.20036222219497,
    277.3441649263664,
    217.7144143900553,
    216.68403166329992,
    336.513714924,
    260.93905791000014,
    256.34053985541493,
    215.5432704674335,
    157.71644667882367,
    134.2935940756251,
    145.67350030695178,
    112.8489662569958,
    146.39758655899502,
    349.11638744800507,
    136.78167904060493,
    178.913682016995,
    384.7697898533864,
    239.99213785750072,
    188.1699639583106,
    203.9328966001948,
    205.449863178555,
    232.90605578935504,
    233.19311099667496,
    147.87910864249994,
    144.05626638000052,
    139.78498933219498,
    110.20322142514496,
    108.48649303681503,
    142.9288472427448,
    246.23229476669997,
    216.37346094229608,
    330.87112913370015,
    184.4741003768048,
    223.18510939699496,
    290.2002785028151,
    216.2592982711905,
    180.55909465012468,
    166.672783995195,
    165.54636867055424,
    147.2868012576852,
    161.24592487171486,
    222.99653703738025,
    253.12404433617505,
    208.63358329135505,
    157.8398132073,
    209.73411688399904,
    194.99128387608025,
    254.21970623438503,
    203.31108387689972,
    259.5244146210004,
    192.68476654735505,
    164.8264289013,
    163.541915709555,
    162.27374610426,
    161.44705629520496,
    172.7603705223004,
    228.9875484298541,
    225.6169286964,
    263.78130373247956,
    218.83179326974476,
    196.4371436260127,
    187.7501572460668,
    167.91008278599992,
    148.63970847019533
  ],
  "weather_applied": false,
  "wind_rel": [
    -0.0,
    -0.0,
    -0.0,
    -0.0,
    -0.0,
    -0.0,
    -0.0,
    -0.0,
    -0.0,
    -0.0,
    -0.0,
    -0.0,
    -0.0,
    -0.0,
    -0.0,
    -0.0,
    -0.0,
    -0.0,
    -0.0,
    -0.0,
    -0.0,
    -0.0,
    -0.0,
    -0.0,
    -0.0,
    -0.0,
    -0.0,
    -0.0,
    -0.0,
    -0.0,
    -0.0,
    -0.0,
    -0.0,
    -0.0,
    -0.0,
    -0.0,
    -0.0,
    -0.0,
    -0.0,
    -0.0,
    -0.0,
    -0.0,
    -0.0,
    -0.0,
    -0.0,
    -0.0,
    -0.0,
    -0.0,
    -0.0,
    -0.0,
    -0.0,
    -0.0,
    -0.0,
    -0.0,
    -0.0,
    -0.0,
    -0.0,
    -0.0,
    -0.0,
    -0.0,
    -0.0,
    -0.0,
    -0.0,
    -0.0,
    -0.0,
    -0.0,
    -0.0,
    -0.0,
    -0.0,
    -0.0,
    -0.0,
    -0.0,
    -0.0,
    -0.0,
    -0.0,
    -0.0,
    -0.0,
    -0.0,
    -0.0,
    -0.0,
    -0.0,
    -0.0,
    -0.0,
    -0.0,
    -0.0,
    -0.0,
    -0.0,
    -0.0,
    -0.0,
    -0.0,
    -0.0,
    -0.0,
    -0.0,
    -0.0,
    -0.0,
    -0.0,
    -0.0,
    -0.0,
    -0.0,
    -0.0,
    -0.0,
    -0.0,
    -0.0,
    -0.0,
    -0.0,
    -0.0,
    -0.0,
    -0.0,
    -0.0,
    -0.0,
    -0.0,
    -0.0,
    -0.0,
    -0.0,
    -0.0,
    -0.0,
    -0.0,
    -0.0,
    -0.0,
    -0.0,
    -0.0,
    -0.0,
    -0.0,
    -0.0,
    -0.0,
    -0.0,
    -0.0,
    -0.0,
    -0.0,
    -0.0,
    -0.0,
    -0.0,
    -0.0,
    -0.0,
    -0.0,
    -0.0,
    -0.0,
    -0.0,
    -0.0,
    -0.0,
    -0.0,
    -0.0,
    -0.0,
    -0.0,
    -0.0,
    -0.0,
    -0.0,
    -0.0,
    -0.0,
    -0.0,
    0.0,
    0.0,
    0.0,
    0.0,
    0.0,
    0.0,
    0.0,
    0.0,
    0.0,
    0.0,
    0.0,
    0.0,
    0.0,
    0.0,
    0.0,
    0.0,
    0.0,
    0.0,
    0.0,
    0.0,
    0.0,
    0.0,
    0.0,
    0.0,
    0.0,
    0.0,
    0.0,
    0.0,
    0.0,
    0.0,
    0.0,
    0.0,
    0.0,
    0.0,
    -0.0,
    -0.0,
    -0.0,
    -0.0,
    -0.0,
    0.0,
    0.0,
    0.0,
    0.0,
    0.0,
    0.0,
    -0.0,
    -0.0,
    -0.0,
    -0.0,
    -0.0,
    -0.0,
    -0.0,
    -0.0,
    -0.0,
    -0.0,
    -0.0,
    -0.0,
    -0.0,
    -0.0,
    -0.0,
    -0.0,
    -0.0,
    -0.0,
    -0.0,
    0.0,
    0.0,
    -0.0,
    -0.0,
    -0.0,
    0.0,
    0.0,
    0.0,
    -0.0,
    0.0,
    0.0,
    0.0,
    0.0,
    0.0,
    0.0,
    0.0,
    0.0,
    0.0,
    0.0,
    0.0,
    0.0,
    0.0,
    0.0,
    0.0,
    0.0,
    0.0,
    0.0,
    0.0,
    0.0,
    0.0,
    0.0,
    0.0,
    0.0,
    0.0,
    0.0,
    0.0,
    -0.0,
    -0.0,
    -0.0,
    -0.0,
    -0.0,
    -0.0,
    -0.0,
    -0.0,
    -0.0,
    -0.0,
    -0.0,
    -0.0,
    -0.0,
    -0.0,
    -0.0,
    -0.0,
    -0.0,
    -0.0,
    -0.0,
    -0.0,
    -0.0,
    -0.0,
    -0.0,
    -0.0,
    -0.0,
    -0.0,
    -0.0,
    -0.0,
    -0.0,
    -0.0,
    -0.0,
    -0.0,
    -0.0,
    -0.0,
    -0.0,
    -0.0,
    -0.0,
    -0.0,
    -0.0,
    -0.0,
    -0.0,
    -0.0,
    -0.0,
    -0.0,
    -0.0,
    -0.0,
    -0.0,
    -0.0,
    -0.0,
    -0.0,
    -0.0,
    -0.0,
    -0.0,
    -0.0,
    -0.0,
    -0.0,
    -0.0,
    -0.0,
    -0.0,
    -0.0,
    -0.0,
    -0.0,
    -0.0,
    -0.0,
    -0.0,
    -0.0,
    -0.0,
    -0.0,
    -0.0,
    -0.0,
    -0.0,
    -0.0,
    -0.0,
    -0.0,
    -0.0,
    -0.0,
    -0.0,
    -0.0,
    -0.0,
    -0.0,
    -0.0,
    -0.0,
    -0.0,
    -0.0,
    -0.0,
    -0.0,
    0.0,
    0.0,
    0.0,
    0.0,
    0.0,
    0.0,
    0.0,
    0.0,
    0.0,
    -0.0,
    -0.0,
    -0.0,
    -0.0,
    -0.0,
    -0.0,
    -0.0,
    -0.0,
    -0.0,
    -0.0,
    -0.0,
    -0.0,
    -0.0,
    -0.0,
    -0.0,
    -0.0,
    -0.0,
    -0.0,
    -0.0,
    -0.0,
    -0.0,
    -0.0,
    -0.0,
    -0.0,
    -0.0,
    -0.0,
    -0.0,
    -0.0,
    -0.0,
    -0.0,
    -0.0,
    0.0,
    -0.0,
    -0.0,
    -0.0,
    -0.0,
    -0.0,
    0.0,
    0.0,
    0.0,
    0.0,
    0.0,
    0.0,
    0.0,
    0.0,
    0.0,
    0.0,
    0.0,
    0.0,
    0.0,
    0.0,
    0.0,
    0.0,
    0.0,
    0.0,
    0.0,
    0.0,
    0.0,
    0.0,
    0.0,
    0.0,
    0.0,
    0.0,
    0.0,
    0.0,
    0.0,
    0.0,
    0.0,
    0.0,
    0.0,
    0.0,
    0.0,
    0.0,
    0.0,
    0.0,
    0.0,
    0.0,
    0.0,
    0.0,
    0.0,
    0.0,
    0.0,
    0.0,
    0.0,
    0.0,
    0.0,
    0.0,
    0.0,
    0.0,
    0.0,
    0.0,
    0.0,
    0.0,
    0.0,
    0.0,
    0.0,
    0.0,
    0.0,
    0.0,
    0.0,
    0.0,
    0.0,
    0.0,
    0.0,
    0.0,
    0.0,
    0.0,
    0.0,
    0.0,
    0.0,
    0.0,
    0.0,
    0.0,
    0.0,
    0.0,
    0.0,
    0.0,
    0.0,
    0.0,
    0.0,
    0.0,
    0.0,
    0.0,
    0.0,
    0.0,
    0.0,
    0.0,
    0.0,
    0.0,
    0.0,
    0.0,
    0.0,
    -0.0,
    -0.0,
    -0.0,
    -0.0,
    -0.0,
    -0.0,
    -0.0,
    -0.0,
    -0.0,
    -0.0,
    -0.0,
    -0.0,
    -0.0,
    -0.0,
    -0.0,
    -0.0,
    -0.0,
    -0.0,
    -0.0,
    -0.0,
    -0.0,
    -0.0,
    -0.0,
    -0.0,
    -0.0,
    -0.0,
    -0.0,
    -0.0,
    -0.0,
    -0.0,
    -0.0,
    -0.0,
    -0.0,
    0.0,
    0.0,
    0.0,
    0.0,
    0.0,
    0.0,
    0.0,
    0.0,
    0.0,
    0.0,
    0.0,
    0.0,
    0.0,
    0.0,
    0.0,
    0.0,
    0.0,
    0.0,
    0.0,
    0.0,
    0.0,
    0.0,
    0.0,
    0.0,
    0.0,
    0.0,
    0.0,
    0.0,
    0.0,
    0.0,
    0.0,
    0.0,
    0.0,
    0.0,
    0.0,
    0.0,
    0.0,
    0.0,
    0.0,
    0.0,
    0.0,
    0.0,
    0.0,
    0.0,
    0.0,
    0.0,
    0.0,
    0.0,
    0.0,
    0.0,
    0.0,
    0.0,
    0.0,
    0.0,
    0.0,
    0.0,
    0.0,
    0.0,
    0.0,
    0.0,
    0.0,
    0.0,
    0.0,
    0.0,
    0.0,
    0.0,
    0.0,
    0.0,
    0.0,
    0.0,
    0.0,
    0.0,
    0.0,
    0.0,
    0.0,
    0.0,
    0.0,
    -0.0,
    -0.0,
    -0.0,
    -0.0,
    -0.0,
    -0.0,
    -0.0,
    -0.0,
    -0.0,
    -0.0,
    0.0,
    0.0,
    0.0,
    0.0,
    0.0,
    0.0,
    0.0,
    0.0,
    0.0,
    0.0,
    0.0,
    0.0,
    -0.0,
    -0.0,
    -0.0,
    -0.0,
    -0.0,
    -0.0,
    -0.0,
    -0.0,
    -0.0,
    -0.0,
    -0.0,
    -0.0,
    -0.0,
    -0.0,
    -0.0,
    -0.0,
    -0.0,
    -0.0,
    -0.0,
    -0.0,
    -0.0,
    -0.0,
    -0.0,
    -0.0,
    -0.0,
    -0.0,
    -0.0,
    -0.0,
    -0.0,
    -0.0,
    -0.0,
    -0.0,
    -0.0,
    -0.0,
    -0.0,
    -0.0,
    -0.0,
    -0.0,
    -0.0,
    -0.0,
    -0.0,
    -0.0,
    -0.0,
    -0.0,
    -0.0,
    -0.0,
    -0.0,
    -0.0,
    -0.0,
    -0.0,
    -0.0,
    -0.0,
    -0.0,
    -0.0,
    -0.0,
    -0.0,
    -0.0,
    -0.0,
    -0.0,
    -0.0,
    0.0,
    0.0,
    0.0,
    0.0,
    0.0,
    0.0,
    0.0,
    0.0,
    0.0,
    0.0,
    0.0,
    0.0,
    0.0,
    0.0,
    -0.0,
    -0.0,
    -0.0,
    -0.0,
    -0.0,
    -0.0,
    -0.0,
    -0.0,
    -0.0,
    -0.0,
    -0.0,
    -0.0,
    -0.0,
    -0.0,
    -0.0,
    -0.0,
    -0.0,
    -0.0,
    -0.0,
    -0.0,
    -0.0,
    -0.0,
    -0.0,
    -0.0,
    -0.0,
    -0.0,
    -0.0,
    -0.0,
    -0.0,
    -0.0,
    -0.0,
    -0.0,
    -0.0,
    -0.0,
    -0.0,
    -0.0,
    -0.0,
    -0.0,
    -0.0,
    -0.0,
    -0.0,
    -0.0,
    -0.0,
    -0.0,
    -0.0,
    -0.0,
    -0.0,
    -0.0,
    -0.0,
    -0.0,
    -0.0,
    -0.0,
    -0.0,
    -0.0,
    -0.0,
    -0.0,
    -0.0,
    -0.0,
    -0.0,
    -0.0,
    -0.0,
    -0.0,
    -0.0,
    -0.0,
    -0.0,
    -0.0,
    -0.0,
    -0.0,
    -0.0,
    -0.0,
    -0.0,
    -0.0,
    -0.0,
    -0.0,
    -0.0,
    -0.0,
    -0.0,
    -0.0,
    -0.0,
    -0.0,
    -0.0,
    -0.0,
    -0.0,
    -0.0,
    -0.0,
    -0.0,
    -0.0,
    -0.0,
    -0.0,
    -0.0,
    -0.0,
    -0.0,
    -0.0,
    -0.0,
    -0.0,
    -0.0,
    -0.0,
    -0.0,
    -0.0,
    -0.0,
    -0.0,
    -0.0,
    -0.0,
    -0.0,
    -0.0,
    -0.0,
    -0.0,
    -0.0,
    0.0,
    0.0,
    0.0,
    0.0,
    0.0,
    0.0,
    0.0,
    0.0,
    0.0,
    0.0,
    0.0,
    0.0,
    0.0,
    0.0,
    0.0,
    0.0,
    0.0,
    0.0,
    0.0,
    0.0,
    0.0,
    0.0,
    0.0,
    0.0,
    0.0,
    0.0,
    0.0,
    0.0,
    0.0,
    0.0,
    0.0,
    0.0,
    0.0,
    0.0,
    0.0,
    0.0,
    0.0,
    0.0,
    0.0,
    0.0,
    0.0,
    0.0,
    0.0,
    0.0,
    0.0,
    0.0,
    0.0,
    0.0,
    0.0,
    0.0,
    0.0,
    0.0,
    0.0,
    0.0,
    0.0,
    0.0,
    0.0,
    0.0,
    0.0,
    0.0,
    0.0,
    0.0,
    0.0,
    0.0,
    0.0,
    0.0,
    0.0,
    0.0,
    0.0,
    0.0,
    0.0,
    0.0,
    0.0,
    0.0,
    0.0,
    0.0,
    0.0,
    0.0,
    0.0,
    0.0,
    0.0,
    0.0,
    0.0,
    0.0,
    0.0,
    0.0,
    0.0,
    0.0,
    0.0,
    0.0,
    0.0,
    0.0,
    0.0,
    0.0,
    0.0,
    0.0,
    0.0,
    0.0,
    0.0,
    0.0,
    0.0,
    0.0,
    0.0,
    0.0,
    0.0,
    0.0,
    0.0,
    0.0,
    0.0,
    0.0,
    0.0,
    0.0,
    0.0,
    0.0,
    0.0,
    0.0,
    0.0,
    0.0,
    0.0,
    0.0,
    -0.0,
    0.0,
    0.0,
    0.0,
    0.0,
    0.0,
    0.0,
    0.0,
    0.0,
    0.0,
    0.0,
    0.0,
    0.0,
    0.0,
    0.0,
    0.0,
    0.0,
    0.0,
    0.0,
    0.0,
    0.0,
    0.0,
    0.0,
    0.0,
    0.0,
    0.0,
    0.0,
    0.0,
    0.0,
    0.0,
    0.0,
    0.0,
    0.0,
    0.0,
    0.0,
    0.0,
    0.0,
    0.0,
    0.0,
    0.0,
    0.0,
    0.0,
    0.0,
    0.0,
    -0.0,
    -0.0,
    -0.0,
    -0.0,
    -0.0,
    -0.0,
    -0.0,
    -0.0,
    -0.0,
    -0.0,
    -0.0,
    -0.0,
    -0.0,
    -0.0,
    -0.0,
    -0.0,
    -0.0,
    -0.0,
    -0.0,
    -0.0,
    -0.0,
    -0.0,
    -0.0,
    -0.0,
    -0.0,
    -0.0,
    -0.0,
    -0.0,
    -0.0,
    -0.0,
    -0.0,
    -0.0,
    -0.0,
    -0.0,
    -0.0,
    -0.0,
    -0.0,
    -0.0,
    -0.0,
    -0.0,
    -0.0,
    -0.0,
    -0.0,
    -0.0,
    -0.0,
    -0.0,
    -0.0,
    -0.0,
    -0.0,
    -0.0,
    -0.0,
    -0.0,
    -0.0,
    -0.0,
    -0.0,
    -0.0,
    -0.0,
    -0.0,
    -0.0,
    -0.0,
    -0.0,
    -0.0,
    -0.0,
    -0.0,
    -0.0,
    -0.0,
    -0.0,
    -0.0,
    -0.0,
    -0.0,
    -0.0,
    -0.0,
    -0.0,
    -0.0,
    -0.0,
    -0.0,
    -0.0,
    -0.0,
    -0.0,
    -0.0,
    -0.0,
    -0.0,
    0.0,
    0.0,
    0.0,
    0.0,
    0.0,
    0.0,
    0.0,
    0.0,
    0.0,
    0.0,
    0.0,
    0.0,
    0.0,
    0.0,
    0.0,
    0.0,
    0.0,
    0.0,
    0.0,
    0.0,
    0.0,
    0.0,
    0.0,
    0.0,
    0.0,
    0.0,
    0.0,
    0.0,
    0.0,
    0.0,
    0.0,
    0.0,
    0.0,
    0.0,
    0.0,
    0.0,
    0.0,
    0.0,
    0.0,
    0.0,
    0.0,
    0.0,
    0.0,
    0.0,
    0.0,
    0.0,
    0.0,
    0.0,
    0.0,
    0.0,
    0.0,
    0.0,
    0.0,
    0.0,
    0.0,
    0.0,
    0.0,
    0.0,
    0.0,
    0.0,
    0.0,
    0.0,
    0.0,
    0.0,
    0.0,
    0.0,
    -0.0,
    -0.0,
    -0.0,
    -0.0,
    -0.0,
    -0.0,
    -0.0,
    -0.0,
    -0.0,
    -0.0,
    -0.0,
    0.0,
    0.0,
    0.0,
    0.0,
    0.0,
    0.0,
    0.0,
    0.0,
    0.0,
    0.0,
    0.0,
    0.0,
    0.0,
    0.0,
    0.0,
    0.0,
    0.0,
    0.0,
    0.0,
    0.0,
    0.0,
    0.0,
    0.0,
    0.0,
    0.0,
    0.0,
    0.0,
    0.0,
    0.0,
    0.0,
    0.0,
    0.0,
    0.0,
    0.0,
    0.0,
    0.0,
    0.0,
    0.0,
    0.0,
    0.0,
    0.0,
    0.0,
    0.0,
    0.0,
    0.0,
    0.0,
    0.0,
    0.0,
    0.0,
    0.0,
    0.0,
    0.0,
    0.0,
    0.0,
    0.0,
    0.0,
    0.0,
    0.0,
    0.0,
    0.0,
    0.0,
    0.0,
    0.0,
    0.0,
    0.0,
    0.0,
    0.0,
    0.0,
    0.0,
    0.0,
    0.0,
    0.0,
    0.0,
    0.0,
    0.0,
    0.0,
    0.0,
    0.0,
    0.0,
    0.0,
    0.0,
    0.0,
    0.0,
    0.0,
    -0.0,
    -0.0,
    -0.0,
    -0.0,
    -0.0,
    -0.0,
    -0.0,
    -0.0,
    -0.0,
    -0.0,
    -0.0,
    -0.0,
    -0.0,
    -0.0,
    -0.0,
    -0.0,
    -0.0,
    -0.0,
    -0.0,
    -0.0,
    -0.0,
    -0.0,
    -0.0,
    -0.0,
    -0.0,
    -0.0,
    -0.0,
    -0.0,
    -0.0,
    -0.0,
    -0.0,
    -0.0,
    -0.0,
    -0.0,
    -0.0,
    -0.0,
    -0.0,
    -0.0,
    -0.0,
    -0.0,
    -0.0,
    -0.0,
    -0.0,
    -0.0,
    -0.0,
    -0.0,
    -0.0,
    -0.0,
    -0.0,
    -0.0,
    -0.0,
    -0.0,
    -0.0,
    -0.0,
    -0.0,
    -0.0,
    -0.0,
    -0.0,
    -0.0,
    -0.0,
    -0.0,
    -0.0,
    -0.0,
    -0.0,
    -0.0,
    -0.0,
    -0.0,
    -0.0,
    -0.0,
    -0.0,
    -0.0,
    -0.0,
    -0.0,
    -0.0,
    0.0,
    0.0,
    0.0,
    0.0,
    0.0,
    0.0,
    0.0,
    0.0,
    -0.0,
    -0.0,
    -0.0,
    -0.0,
    -0.0,
    -0.0,
    -0.0,
    -0.0,
    -0.0,
    -0.0,
    -0.0,
    -0.0,
    -0.0,
    -0.0,
    -0.0,
    -0.0,
    0.0,
    0.0,
    0.0,
    0.0,
    0.0,
    0.0,
    0.0,
    0.0,
    0.0,
    0.0,
    0.0,
    0.0,
    0.0,
    0.0,
    0.0,
    0.0,
    0.0,
    0.0,
    0.0,
    0.0,
    0.0,
    0.0,
    0.0,
    0.0,
    0.0,
    0.0,
    0.0,
    0.0,
    0.0,
    0.0,
    0.0,
    0.0,
    0.0,
    0.0,
    0.0,
    0.0,
    0.0,
    0.0,
    0.0,
    0.0,
    0.0,
    0.0,
    0.0,
    0.0,
    0.0,
    0.0,
    0.0,
    0.0,
    0.0,
    0.0,
    0.0,
    0.0,
    -0.0,
    0.0,
    0.0,
    0.0,
    0.0,
    0.0,
    0.0,
    0.0,
    0.0,
    0.0,
    0.0,
    0.0,
    0.0,
    0.0,
    0.0,
    0.0,
    0.0,
    0.0,
    0.0,
    0.0,
    0.0,
    0.0,
    0.0,
    0.0,
    0.0,
    0.0,
    0.0,
    0.0,
    0.0,
    0.0,
    0.0,
    0.0,
    0.0,
    0.0,
    0.0,
    0.0,
    0.0,
    0.0,
    0.0,
    0.0,
    0.0,
    0.0,
    0.0,
    0.0,
    0.0,
    0.0,
    0.0,
    0.0,
    0.0,
    0.0,
    0.0,
    0.0,
    0.0,
    0.0,
    0.0,
    0.0,
    0.0,
    0.0,
    0.0,
    0.0,
    0.0,
    0.0,
    0.0,
    0.0,
    0.0,
    0.0,
    0.0,
    0.0,
    0.0,
    0.0,
    0.0,
    0.0,
    0.0,
    0.0,
    0.0,
    0.0,
    0.0,
    0.0,
    0.0,
    0.0,
    0.0,
    0.0,
    0.0,
    0.0,
    0.0,
    0.0,
    0.0,
    0.0,
    0.0,
    0.0,
    0.0,
    0.0,
    0.0,
    0.0,
    0.0,
    0.0,
    0.0,
    0.0,
    0.0,
    -0.0,
    -0.0,
    -0.0,
    -0.0,
    -0.0,
    -0.0,
    -0.0,
    -0.0,
    -0.0,
    -0.0,
    -0.0,
    -0.0,
    -0.0,
    -0.0,
    -0.0,
    -0.0,
    -0.0,
    -0.0,
    -0.0,
    -0.0,
    -0.0,
    -0.0,
    -0.0,
    -0.0,
    -0.0,
    -0.0,
    -0.0,
    -0.0,
    -0.0,
    -0.0,
    -0.0,
    -0.0,
    -0.0,
    -0.0,
    -0.0,
    -0.0,
    -0.0,
    -0.0,
    -0.0,
    -0.0,
    -0.0,
    -0.0,
    -0.0,
    -0.0,
    -0.0,
    -0.0,
    -0.0,
    -0.0,
    -0.0,
    -0.0,
    -0.0,
    -0.0,
    -0.0,
    -0.0,
    -0.0,
    -0.0,
    -0.0,
    -0.0,
    -0.0,
    -0.0,
    -0.0,
    -0.0,
    -0.0,
    -0.0,
    -0.0,
    -0.0,
    0.0,
    0.0,
    0.0,
    0.0,
    0.0,
    0.0,
    0.0,
    0.0,
    0.0,
    0.0,
    0.0,
    0.0,
    0.0,
    0.0,
    0.0,
    0.0,
    0.0,
    0.0,
    0.0,
    0.0,
    0.0,
    0.0,
    0.0,
    0.0,
    0.0,
    0.0,
    0.0,
    0.0,
    0.0,
    0.0,
    0.0,
    0.0,
    0.0,
    0.0,
    0.0,
    0.0,
    0.0,
    0.0,
    0.0,
    0.0,
    0.0,
    0.0,
    0.0,
    0.0,
    0.0,
    0.0,
    0.0,
    0.0,
    0.0,
    0.0,
    0.0,
    -0.0,
    -0.0,
    -0.0,
    -0.0,
    -0.0,
    -0.0,
    -0.0,
    -0.0,
    -0.0,
    -0.0,
    -0.0,
    -0.0,
    -0.0,
    -0.0,
    -0.0,
    -0.0,
    -0.0,
    -0.0,
    -0.0,
    -0.0,
    -0.0,
    -0.0,
    -0.0,
    -0.0,
    -0.0,
    -0.0,
    -0.0,
    -0.0,
    -0.0,
    -0.0,
    -0.0,
    -0.0,
    -0.0,
    -0.0,
    -0.0,
    -0.0,
    -0.0,
    -0.0,
    -0.0,
    -0.0,
    -0.0,
    -0.0,
    -0.0,
    -0.0,
    -0.0,
    -0.0,
    -0.0,
    -0.0,
    -0.0,
    -0.0,
    -0.0,
    -0.0,
    -0.0,
    -0.0,
    -0.0,
    -0.0,
    -0.0,
    -0.0,
    -0.0,
    -0.0,
    -0.0,
    -0.0,
    -0.0,
    -0.0,
    -0.0,
    -0.0,
    -0.0,
    -0.0,
    -0.0,
    -0.0,
    -0.0,
    -0.0,
    -0.0,
    -0.0,
    -0.0,
    -0.0,
    -0.0,
    -0.0,
    -0.0,
    -0.0,
    -0.0,
    -0.0,
    -0.0,
    -0.0,
    -0.0,
    -0.0,
    -0.0,
    -0.0,
    -0.0,
    -0.0,
    -0.0,
    -0.0,
    -0.0,
    -0.0,
    -0.0,
    -0.0,
    -0.0,
    -0.0,
    -0.0,
    -0.0,
    -0.0,
    -0.0,
    -0.0,
    -0.0,
    -0.0,
    -0.0,
    -0.0,
    -0.0,
    -0.0,
    -0.0,
    -0.0,
    -0.0,
    -0.0,
    -0.0,
    -0.0,
    -0.0,
    -0.0,
    -0.0,
    -0.0,
    -0.0,
    -0.0,
    -0.0,
    -0.0,
    -0.0,
    -0.0,
    -0.0,
    -0.0,
    -0.0,
    -0.0,
    -0.0,
    -0.0,
    -0.0,
    -0.0,
    -0.0,
    -0.0,
    -0.0,
    -0.0,
    -0.0,
    -0.0,
    -0.0,
    -0.0,
    -0.0,
    -0.0,
    -0.0,
    -0.0,
    -0.0,
    -0.0,
    -0.0,
    -0.0,
    -0.0,
    -0.0,
    -0.0,
    -0.0,
    -0.0,
    -0.0,
    -0.0,
    -0.0,
    -0.0,
    -0.0,
    -0.0,
    -0.0,
    -0.0,
    -0.0
  ],
  "repr_kind": "object_v3",
  "debug": {
    "reason": "ok",
    "force_recompute": true,
    "persist_ignored": true,
    "ignored_persist": true,
    "used_fallback": false,
    "weather_applied": false,
    "weather_source": "neutral",
    "estimat_cfg_used": {
      "force": true
    },
    "input_candidates": {
      "debug_session": "C:\\Users\\easy2\\OneDrive\\Skrivebord\\Archieve\\Karriere\\CycleGraph\\_debug\\session_16231049823.json",
      "debug_result": "C:\\Users\\easy2\\OneDrive\\Skrivebord\\Archieve\\Karriere\\CycleGraph\\_debug\\result_16231049823.json",
      "results": "C:\\Users\\easy2\\OneDrive\\Skrivebord\\Archieve\\Karriere\\CycleGraph\\logs\\results\\result_16231049823.json",
      "inline_samples": "C:\\Users\\easy2\\OneDrive\\Skrivebord\\Archieve\\Karriere\\CycleGraph\\logs\\inline_samples_16231049823.json",
      "actual10_latest_session": "C:\\Users\\easy2\\OneDrive\\Skrivebord\\Archieve\\Karriere\\CycleGraph\\logs\\actual10\\latest\\session_16231049823.json",
      "raw_streams": "C:\\Users\\easy2\\OneDrive\\Skrivebord\\Archieve\\Karriere\\CycleGraph\\data\\raw\\streams_16231049823.json",
      "raw_activity": "C:\\Users\\easy2\\OneDrive\\Skrivebord\\Archieve\\Karriere\\CycleGraph\\data\\raw\\activity_16231049823.json",
      "gpx": "C:\\Users\\easy2\\OneDrive\\Skrivebord\\Archieve\\Karriere\\CycleGraph\\data\\gpx\\16231049823.gpx"
    },
    "input_exists": {
      "debug_session": true,
      "debug_result": true,
      "results": true,
      "inline_samples": true,
      "actual10_latest_session": true,
      "raw_streams": true,
      "raw_activity": true,
      "gpx": true
    },
    "input_used": "C:\\Users\\easy2\\OneDrive\\Skrivebord\\Archieve\\Karriere\\CycleGraph\\_debug\\session_16231049823.json",
    "samples_len": 1727,
    "streams_probe": null
  },
  "weather_source": "neutral",
  "profile_version": "v1-5403a6cd-20260101",
  "profile_used": {
    "rider_weight_kg": 85,
    "bike_weight_kg": 8.0,
    "weight_kg": 93.0,
    "total_weight_kg": 93.0,
    "bike_type": "road",
    "tire_width_mm": 28,
    "tire_quality": "performance",
    "device": "strava",
    "profile_version": "v1-5403a6cd-20260101",
    "cda": 0.3,
    "crr": 0.004,
    "crank_efficiency": 0.96
  }
}