{
  "calibrated": false,
  "cg_build": "T15-cg_build-20251216",
  "metrics": {
    "cg_build": "T15-cg_build-20251216",
    "core_n_device_samples": 0,
    "core_watts_source": "disabled_no_powermeter",
    "drag_watt": 120.89251357750965,
    "eff_used": 0.955,
    "gravity_watt": 0.5953778682019778,
    "gravity_watt_pedal": 59.06807239328639,
    "model_watt_crank": 154.50961811473644,
    "model_watt_wheel": 147.5566852995733,
    "model_watt_wheel_pedal": 209.93090086445702,
    "model_watt_wheel_pedal_elapsed": 204.50025073163633,
    "model_watt_wheel_pedal_moving": 209.93090086445702,
    "pedal_ratio_elapsed_over_moving": 0.9741312493279538,
    "precision_watt": 154.50961811473644,
    "precision_watt_avg": 147.5566852995733,
    "precision_watt_crank": 154.50961811473644,
    "precision_watt_pedal": 219.82293284236337,
    "profile_used": {
      "rider_weight_kg": 78.0,
      "bike_weight_kg": 8.0,
      "weight_kg": 86.0,
      "total_weight_kg": 86.0,
      "cda": 0.3,
      "crr": 0.004,
      "crank_eff_pct": 95.5,
      "device": "strava",
      "notes": "Trinn5 default; rediger fritt.",
      "profile_version": "v1-883d8daf-20251228"
    },
    "rolling_watt": 26.06879385386169,
    "total_watt": 147.5566852995733,
    "total_watt_pedal": 209.93090086445702,
    "wind_effect": 0.55,
    "precision_watt_signed": 147.5566852995733,
    "total_watt_signed": 147.5566852995733,
    "gravity_watt_signed": 0.5953778682019778,
    "model_watt_wheel_signed": 147.5566852995733,
    "calibration_mae": null,
    "calibrated": false,
    "calibration_status": "not_available",
    "estimated_error_pct_range": [
      null,
      null
    ],
    "precision_quality_hint": "no-heuristics-available",
    "weather_applied": false
  },
  "precision_watt_avg": 219.82293284236337,
  "source": "rust_1arg",
  "v_rel": [
    0.1,
    0.1,
    0.1,
    7.05,
    8.16,
    9.1,
    9.767,
    10.317,
    10.517,
    9.983,
    9.583,
    9.24,
    9.5,
    9.25,
    8.6,
    8.271,
    7.94,
    7.933,
    7.933,
    8.12,
    7.66,
    7.48,
    7.467,
    7.55,
    7.56,
    7.833,
    7.814,
    7.862,
    7.95,
    7.98,
    7.783,
    7.329,
    7.05,
    6.8,
    7.017,
    7.6,
    8.442,
    8.962,
    9.4,
    9.55,
    9.843,
    9.764,
    9.825,
    9.98,
    9.912,
    9.77,
    9.591,
    9.325,
    9.244,
    8.833,
    7.857,
    7.3,
    6.9,
    6.6,
    6.389,
    4.9,
    5.68,
    6.833,
    7.014,
    8.067,
    9.4,
    9.533,
    10.2,
    10.243,
    10.517,
    10.55,
    10.557,
    10.522,
    10.475,
    10.51,
    10.264,
    9.957,
    9.763,
    9.742,
    9.775,
    10.013,
    9.918,
    9.833,
    10.029,
    10.267,
    10.287,
    10.237,
    10.15,
    9.745,
    9.47,
    9.436,
    8.486,
    8.313,
    7.867,
    7.757,
    7.712,
    7.383,
    7.229,
    6.78,
    6.72,
    7.425,
    7.687,
    8.3,
    9.129,
    9.311,
    9.883,
    10.414,
    10.657,
    10.738,
    10.45,
    9.8,
    9.7,
    9.686,
    9.833,
    10.04,
    11.48,
    11.833,
    10.867,
    10.3,
    10.229,
    10.1,
    9.94,
    9.783,
    9.417,
    8.9,
    8.756,
    7.483,
    7.929,
    8.438,
    8.7,
    8.962,
    9.078,
    9.11,
    9.243,
    9.186,
    9.28,
    9.333,
    9.233,
    9.189,
    8.967,
    8.863,
    8.6,
    8.608,
    8.487,
    8.543,
    8.4,
    8.229,
    8.26,
    8.188,
    8.083,
    8.05,
    8.067,
    8.2,
    8.517,
    8.52,
    8.52,
    8.514,
    8.4,
    8.34,
    8.6,
    8.713,
    8.6,
    8.4,
    8.375,
    8.383,
    8.455,
    8.529,
    8.7,
    8.56,
    8.45,
    8.04,
    8.244,
    8.22,
    8.114,
    8.082,
    8.008,
    7.9,
    7.967,
    8.0,
    8.087,
    8.156,
    7.829,
    7.543,
    7.175,
    7.044,
    7.0,
    6.36,
    7.28,
    7.74,
    8.62,
    9.92,
    10.6,
    10.743,
    8.237,
    7.3,
    7.337,
    7.311,
    7.06,
    7.02,
    7.313,
    7.583,
    8.115,
    8.577,
    9.082,
    9.357,
    9.533,
    9.762,
    9.98,
    10.314,
    10.371,
    10.85,
    10.95,
    11.271,
    11.257,
    11.262,
    10.971,
    10.9,
    10.843,
    10.171,
    9.81,
    9.32,
    9.267,
    9.033,
    8.871,
    8.014,
    7.522,
    7.1,
    6.94,
    6.743,
    6.475,
    6.183,
    6.171,
    5.333,
    4.8,
    4.48,
    4.143,
    3.58,
    3.829,
    3.98,
    4.025,
    4.067,
    4.0,
    3.96,
    3.957,
    3.98,
    3.96,
    3.942,
    3.911,
    3.38,
    3.45,
    4.0,
    4.27,
    4.05,
    3.644,
    3.612,
    3.7,
    3.833,
    3.8,
    3.817,
    3.833,
    4.292,
    4.72,
    4.775,
    4.933,
    5.02,
    5.05,
    5.583,
    5.671,
    6.16,
    6.72,
    7.389,
    7.917,
    7.388,
    7.175,
    7.078,
    6.97,
    6.845,
    6.0,
    5.38,
    5.35,
    5.45,
    5.486,
    5.417,
    5.667,
    6.25,
    7.0,
    7.408,
    7.862,
    8.43,
    8.415,
    8.36,
    8.4,
    8.333,
    7.96,
    7.886,
    8.117,
    8.429,
    8.829,
    9.06,
    9.15,
    9.05,
    9.14,
    9.14,
    10.0,
    10.18,
    10.386,
    10.425,
    10.325,
    10.257,
    10.314,
    10.25,
    9.967,
    9.893,
    9.837,
    9.957,
    9.44,
    8.6,
    8.14,
    7.983,
    7.862,
    7.533,
    7.383,
    7.36,
    7.35,
    7.717,
    8.02,
    8.26,
    8.45,
    8.543,
    8.75,
    8.88,
    9.43,
    9.6,
    9.54,
    9.683,
    10.04,
    10.275,
    10.34,
    10.814,
    10.917,
    10.862,
    10.862,
    10.943,
    11.186,
    11.257,
    11.32,
    11.6,
    11.55,
    11.086,
    10.943,
    10.778,
    10.42,
    10.083,
    10.06,
    10.171,
    9.82,
    10.04,
    9.92,
    9.95,
    9.88,
    10.08,
    10.38,
    10.78,
    11.18,
    11.56,
    12.54,
    13.28,
    14.14,
    14.52,
    14.583,
    14.714,
    15.1,
    15.267,
    15.7,
    15.8,
    15.117,
    14.92,
    14.771,
    14.3,
    14.28,
    13.64,
    13.12,
    12.313,
    11.18,
    9.183,
    8.429,
    8.275,
    8.089,
    6.92,
    5.56,
    5.28,
    5.217,
    5.2,
    5.183,
    4.983,
    4.78,
    4.667,
    4.583,
    4.4,
    4.133,
    3.94,
    3.9,
    4.044,
    3.957,
    3.92,
    3.733,
    3.75,
    3.771,
    3.8,
    3.814,
    3.617,
    3.6,
    3.412,
    3.513,
    3.62,
    3.487,
    3.867,
    3.943,
    3.657,
    3.758,
    4.46,
    5.133,
    5.138,
    5.14,
    5.15,
    5.383,
    5.64,
    6.333,
    6.82,
    6.85,
    6.9,
    7.033,
    7.3,
    7.892,
    8.3,
    8.971,
    8.87,
    8.488,
    8.367,
    8.5,
    8.511,
    8.833,
    9.28,
    9.133,
    8.414,
    7.65,
    7.343,
    7.183,
    7.025,
    6.925,
    6.91,
    7.056,
    7.387,
    7.7,
    8.614,
    8.49,
    8.28,
    8.712,
    8.756,
    8.7,
    8.583,
    8.2,
    8.075,
    7.956,
    7.65,
    7.143,
    7.046,
    7.108,
    7.256,
    7.243,
    6.486,
    5.967,
    5.517,
    5.1,
    5.083,
    4.8,
    4.46,
    4.48,
    4.75,
    4.783,
    4.786,
    4.811,
    4.68,
    4.633,
    4.683,
    4.583,
    4.557,
    4.7,
    4.714,
    4.96,
    4.72,
    4.767,
    5.04,
    5.48,
    5.54,
    5.483,
    5.5,
    5.66,
    5.68,
    5.7,
    5.72,
    5.96,
    6.24,
    6.513,
    6.678,
    6.94,
    7.133,
    7.145,
    7.189,
    7.383,
    7.311,
    7.311,
    7.5,
    7.513,
    7.55,
    7.5,
    7.478,
    7.592,
    7.856,
    7.95,
    7.84,
    7.927,
    8.058,
    8.083,
    7.76,
    7.62,
    7.229,
    7.354,
    7.71,
    8.983,
    9.88,
    10.5,
    10.617,
    11.44,
    11.5,
    11.457,
    11.3,
    11.22,
    11.15,
    11.14,
    11.14,
    11.217,
    11.9,
    12.143,
    12.162,
    12.567,
    12.8,
    12.856,
    13.08,
    13.043,
    12.82,
    12.86,
    12.967,
    13.24,
    13.7,
    13.76,
    13.433,
    13.317,
    13.288,
    13.233,
    13.0,
    12.883,
    12.4,
    12.1,
    11.9,
    11.517,
    11.42,
    11.114,
    11.044,
    10.683,
    11.017,
    11.4,
    11.64,
    11.58,
    11.4,
    11.35,
    11.2,
    10.82,
    10.783,
    10.717,
    10.74,
    10.667,
    10.529,
    10.382,
    10.29,
    10.6,
    10.675,
    10.756,
    11.3,
    11.433,
    11.76,
    12.02,
    12.42,
    12.68,
    12.9,
    12.98,
    13.1,
    12.16,
    11.5,
    10.92,
    11.017,
    10.98,
    10.767,
    10.56,
    10.4,
    11.12,
    11.74,
    11.94,
    10.68,
    9.9,
    9.4,
    9.317,
    7.3,
    6.78,
    6.638,
    5.943,
    5.327,
    5.06,
    5.082,
    4.629,
    3.98,
    3.8,
    3.845,
    3.907,
    3.778,
    3.571,
    3.444,
    3.386,
    3.617,
    3.54,
    3.8,
    3.817,
    4.08,
    4.4,
    4.386,
    4.2,
    4.183,
    4.15,
    4.383,
    4.44,
    4.65,
    4.64,
    4.35,
    4.429,
    4.487,
    4.7,
    4.94,
    4.92,
    5.08,
    5.2,
    5.3,
    5.25,
    5.244,
    5.3,
    5.74,
    6.289,
    6.66,
    6.86,
    6.6,
    6.586,
    6.737,
    6.52,
    6.42,
    6.68,
    6.74,
    6.68,
    6.86,
    6.96,
    6.96,
    6.62,
    6.475,
    6.317,
    6.18,
    6.24,
    6.229,
    6.28,
    6.267,
    6.2,
    6.3,
    6.3,
    6.567,
    6.722,
    6.84,
    7.2,
    7.329,
    7.85,
    8.369,
    9.133,
    9.237,
    10.0,
    10.38,
    10.5,
    11.14,
    11.067,
    10.789,
    10.891,
    11.2,
    11.338,
    11.78,
    11.88,
    11.4,
    10.886,
    10.737,
    9.633,
    9.24,
    8.614,
    8.383,
    8.222,
    7.786,
    7.791,
    7.9,
    8.32,
    8.114,
    7.84,
    7.929,
    8.21,
    8.729,
    8.85,
    8.922,
    9.733,
    10.02,
    10.08,
    10.26,
    10.383,
    10.58,
    11.66,
    12.26,
    12.3,
    12.4,
    12.26,
    12.283,
    12.22,
    11.971,
    12.037,
    11.967,
    11.933,
    11.833,
    11.62,
    11.886,
    12.12,
    12.46,
    12.533,
    12.7,
    12.7,
    12.833,
    13.14,
    13.28,
    13.76,
    13.78,
    13.557,
    13.45,
    13.367,
    13.04,
    13.08,
    12.957,
    12.68,
    12.5,
    12.44,
    12.44,
    12.433,
    12.45,
    12.614,
    12.91,
    13.133,
    13.157,
    13.244,
    13.6,
    13.883,
    14.343,
    14.6,
    14.34,
    12.914,
    12.383,
    11.233,
    11.1,
    10.813,
    10.444,
    10.186,
    10.037,
    10.213,
    10.41,
    11.32,
    11.7,
    12.2,
    12.183,
    12.12,
    12.033,
    11.74,
    11.357,
    11.278,
    11.15,
    10.962,
    9.957,
    9.586,
    8.8,
    8.709,
    8.815,
    8.814,
    8.662,
    8.489,
    8.37,
    7.18,
    7.08,
    7.0,
    7.233,
    7.867,
    8.41,
    8.671,
    8.737,
    8.77,
    8.789,
    8.744,
    8.756,
    8.8,
    8.736,
    8.879,
    9.133,
    9.4,
    9.5,
    9.557,
    9.417,
    8.92,
    8.486,
    7.991,
    7.825,
    7.736,
    7.5,
    7.457,
    7.19,
    7.127,
    7.4,
    7.629,
    7.567,
    7.571,
    7.789,
    7.973,
    8.082,
    8.01,
    8.08,
    8.033,
    8.04,
    8.156,
    8.189,
    8.214,
    8.164,
    8.256,
    8.388,
    8.409,
    8.3,
    8.22,
    7.825,
    7.98,
    8.167,
    8.158,
    8.1,
    8.157,
    8.054,
    7.873,
    7.85,
    8.363,
    8.62,
    8.983,
    9.089,
    9.022,
    9.289,
    9.363,
    9.291,
    9.125,
    9.1,
    9.088,
    9.067,
    9.471,
    9.715,
    9.85,
    9.713,
    9.692,
    9.7,
    9.875,
    9.943,
    10.09,
    9.637,
    9.186,
    9.243,
    9.3,
    9.314,
    9.275,
    9.237,
    8.92,
    8.667,
    8.643,
    8.34,
    8.333,
    8.363,
    8.6,
    8.6,
    8.2,
    8.313,
    8.473,
    8.629,
    8.82,
    9.03,
    8.93,
    8.678,
    8.762,
    8.76,
    8.329,
    7.925,
    7.871,
    8.1,
    8.325,
    8.38,
    8.52,
    8.6,
    8.662,
    8.563,
    8.556,
    8.58,
    8.536,
    8.217,
    7.86,
    7.76,
    7.717,
    7.313,
    7.35,
    7.467,
    7.42,
    7.186,
    6.989,
    7.2,
    7.475,
    7.4,
    7.217,
    7.2,
    7.238,
    7.511,
    7.55,
    7.3,
    7.175,
    7.338,
    7.427,
    7.478,
    7.612,
    8.02,
    7.989,
    7.825,
    7.61,
    7.563,
    7.564,
    7.733,
    7.836,
    7.838,
    7.829,
    7.744,
    7.4,
    7.443,
    7.47,
    6.943,
    6.8,
    6.44,
    6.38,
    5.72,
    5.543,
    5.138,
    4.633,
    4.217,
    4.088,
    3.686,
    3.729,
    3.733,
    3.633,
    3.55,
    3.62,
    3.618,
    3.554,
    3.509,
    3.392,
    3.317,
    3.213,
    2.975,
    3.014,
    3.025,
    3.54,
    3.54,
    3.24,
    3.14,
    2.9,
    2.986,
    3.129,
    3.05,
    2.84,
    2.883,
    2.98,
    3.0,
    3.133,
    3.04,
    2.914,
    3.057,
    3.075,
    2.817,
    2.811,
    2.94,
    2.971,
    3.071,
    3.083,
    3.044,
    2.983,
    3.0,
    2.967,
    2.833,
    2.733,
    2.98,
    2.986,
    2.971,
    2.967,
    2.814,
    2.9,
    3.033,
    3.114,
    3.213,
    3.211,
    3.233,
    3.357,
    3.4,
    3.483,
    3.657,
    3.783,
    4.156,
    4.175,
    4.14,
    4.25,
    4.35,
    4.244,
    4.21,
    4.183,
    4.067,
    3.97,
    3.94,
    3.957,
    4.071,
    4.1,
    4.32,
    4.344,
    4.411,
    4.48,
    4.486,
    4.4,
    4.543,
    4.575,
    4.588,
    4.671,
    4.65,
    4.767,
    4.843,
    4.633,
    4.5,
    4.362,
    0.1,
    0.1,
    0.1,
    6.0,
    6.214,
    6.933,
    7.467,
    7.543,
    8.36,
    8.62,
    9.025,
    10.06,
    10.317,
    10.486,
    11.367,
    11.88,
    12.22,
    12.783,
    13.38,
    13.82,
    14.417,
    15.02,
    15.42,
    15.68,
    15.733,
    16.36,
    16.48,
    16.56,
    16.52,
    16.54,
    16.533,
    16.529,
    16.42,
    16.367,
    16.3,
    16.06,
    15.36,
    14.78,
    14.633,
    14.529,
    14.033,
    13.62,
    13.52,
    13.517,
    13.283,
    12.667,
    12.014,
    11.06,
    10.0,
    9.32,
    9.067,
    7.917,
    7.34,
    6.4,
    6.057,
    5.729,
    5.612,
    5.489,
    5.443,
    5.8,
    5.957,
    5.975,
    6.12,
    6.479,
    6.647,
    6.72,
    7.06,
    6.767,
    6.375,
    5.8,
    5.743,
    5.271,
    4.9,
    4.917,
    4.657,
    4.614,
    4.667,
    4.61,
    4.46,
    4.5,
    4.643,
    4.386,
    4.392,
    4.446,
    4.467,
    4.456,
    4.462,
    4.456,
    4.788,
    4.96,
    5.487,
    5.7,
    6.22,
    6.675,
    7.518,
    7.762,
    8.343,
    8.722,
    9.467,
    9.86,
    10.25,
    10.36,
    10.9,
    11.033,
    11.125,
    11.6,
    11.96,
    12.033,
    12.42,
    12.74,
    13.083,
    13.58,
    13.55,
    13.483,
    13.317,
    13.32,
    13.438,
    13.7,
    13.767,
    14.35,
    14.66,
    14.82,
    14.833,
    14.58,
    13.24,
    12.967,
    12.02,
    11.683,
    11.429,
    9.78,
    8.417,
    7.92,
    7.867,
    7.688,
    7.2,
    7.057,
    6.738,
    6.06,
    6.05,
    5.563,
    5.463,
    5.2,
    5.122,
    4.82,
    4.737,
    4.367,
    4.392,
    4.45,
    4.392,
    4.2,
    4.138,
    4.1,
    3.95,
    3.963,
    3.91,
    3.909,
    4.287,
    4.436,
    4.61,
    4.746,
    4.776,
    4.821,
    4.888,
    5.2,
    5.389,
    5.386,
    5.9,
    6.475,
    6.5,
    6.767,
    6.9,
    7.336,
    7.731,
    8.056,
    8.58,
    8.988,
    9.05,
    9.4,
    9.383,
    9.689,
    9.763,
    9.663,
    9.612,
    9.582,
    9.8,
    9.814,
    9.68,
    8.93,
    8.478,
    8.43,
    7.56,
    7.245,
    7.088,
    6.9,
    6.833,
    6.743,
    6.32,
    6.32,
    6.35,
    6.314,
    6.26,
    6.25,
    6.46,
    7.188,
    7.429,
    7.667,
    7.78,
    8.68,
    8.8,
    8.92,
    9.1,
    9.24,
    9.283,
    9.5,
    9.9,
    10.086,
    10.125,
    10.6,
    10.662,
    10.67,
    10.8,
    11.012,
    11.044,
    11.283,
    11.46,
    11.66,
    11.8,
    11.833,
    12.057,
    12.28,
    12.457,
    12.6,
    12.3,
    11.886,
    11.633,
    10.84,
    10.35,
    9.59,
    9.375,
    9.175,
    9.088,
    8.98,
    8.733,
    8.678,
    7.78,
    7.22,
    6.386,
    6.167,
    5.74,
    5.614,
    5.467,
    5.385,
    5.593,
    6.12,
    6.731,
    6.94,
    7.329,
    7.59,
    7.717,
    8.167,
    9.0,
    8.813,
    9.0,
    9.263,
    9.189,
    8.938,
    8.15,
    7.917,
    7.825,
    7.26,
    7.25,
    6.75,
    6.567,
    6.514,
    6.456,
    6.28,
    6.44,
    6.56,
    6.68,
    7.0,
    8.467,
    8.96,
    9.029,
    8.95,
    8.92,
    8.42,
    8.48,
    8.85,
    8.867,
    8.883,
    8.878,
    8.9,
    9.12,
    9.56,
    9.5,
    9.567,
    9.629,
    10.06,
    10.086,
    10.087,
    10.186,
    10.04,
    9.717,
    9.74,
    9.48,
    9.338,
    9.412,
    9.64,
    9.729,
    10.387,
    10.8,
    11.15,
    11.257,
    11.288,
    11.74,
    11.92,
    11.86,
    11.96,
    12.083,
    12.3,
    12.46,
    12.28,
    12.183,
    11.5,
    9.9,
    9.617,
    9.188,
    9.088,
    8.8,
    8.656,
    8.083,
    8.02,
    7.85,
    7.455,
    7.4,
    7.6,
    7.715,
    7.627,
    7.592,
    7.46,
    7.571,
    7.762,
    7.743,
    7.525,
    7.344,
    7.4,
    7.208,
    6.68,
    6.42,
    6.386,
    6.28,
    6.214,
    6.271,
    6.413,
    6.764,
    7.188,
    8.18,
    8.68,
    8.783,
    9.72,
    10.02,
    10.133,
    10.175,
    10.5,
    10.46,
    10.667,
    11.3,
    12.157,
    12.25,
    12.257,
    12.2,
    12.133,
    11.1,
    10.478,
    9.983,
    9.667,
    9.1,
    9.083,
    8.8,
    8.45,
    8.282,
    8.123,
    8.01,
    8.36,
    8.35,
    8.38,
    7.96,
    8.18,
    7.967,
    7.92,
    7.871,
    8.367,
    8.657,
    8.933,
    9.3,
    9.35,
    9.45,
    9.88,
    11.0,
    11.62,
    11.786,
    12.15,
    12.517,
    12.817,
    13.24,
    13.217,
    12.86,
    12.613,
    12.322,
    12.075,
    11.678,
    11.578,
    11.256,
    11.125,
    10.912,
    10.756,
    10.533,
    10.41,
    10.167,
    9.829,
    9.76,
    9.26,
    9.3,
    9.73,
    9.917,
    10.422,
    10.82,
    10.843,
    10.9,
    11.2,
    11.25,
    11.54,
    12.32,
    13.62,
    13.68,
    13.683,
    13.671,
    13.733,
    13.84,
    13.8,
    13.9,
    13.9,
    14.017,
    14.26,
    14.18,
    14.12,
    14.24,
    14.3,
    14.5,
    14.529,
    14.76,
    14.78,
    14.52,
    14.24,
    13.04,
    13.1,
    13.82,
    13.383,
    13.825,
    13.917,
    14.62,
    14.18,
    13.5,
    12.22,
    10.909,
    10.6,
    9.76,
    9.188,
    8.133,
    7.563,
    6.26,
    5.88,
    6.08,
    6.129,
    6.42,
    6.467,
    1.117,
    2.589,
    2.589,
    6.033,
    6.743,
    6.9,
    7.05,
    7.229,
    7.3,
    7.136,
    6.443,
    6.4,
    6.614,
    6.137,
    6.022,
    6.15,
    5.909,
    5.825,
    5.62,
    6.04,
    6.2,
    6.167,
    6.417,
    6.9,
    7.667,
    7.843,
    7.92,
    7.52,
    7.612,
    7.92,
    8.533,
    8.975,
    9.183,
    9.35,
    9.41,
    9.183,
    9.056,
    9.125,
    8.75,
    8.7,
    8.9,
    8.93,
    8.883,
    9.057,
    9.15,
    8.76,
    8.525,
    8.75,
    8.875,
    8.922,
    9.58,
    9.68,
    9.757,
    9.88,
    9.88,
    9.75,
    9.33,
    9.1,
    8.583,
    8.444,
    8.26,
    8.25,
    8.08,
    8.2,
    8.37,
    8.343,
    8.262,
    8.3,
    8.38,
    8.343,
    8.311,
    8.136,
    7.967,
    8.0,
    7.831,
    7.725,
    8.067,
    7.97,
    7.725,
    7.0,
    6.155,
    5.314,
    5.12,
    5.1,
    5.787,
    5.96,
    5.84,
    5.614,
    5.3,
    5.58,
    2.9,
    2.783,
    3.9,
    4.1,
    4.746,
    5.445,
    5.9,
    5.3,
    3.7,
    3.46,
    3.5,
    3.74,
    4.073,
    4.13,
    4.167,
    4.4,
    3.833,
    3.89,
    3.629,
    3.443,
    3.4,
    3.427,
    3.229,
    3.075,
    3.143,
    3.722,
    4.286,
    4.7,
    4.936,
    5.0,
    4.99,
    4.973,
    4.86,
    4.82,
    4.58,
    4.483,
    5.38,
    6.327,
    6.886,
    6.878,
    6.5,
    6.112,
    5.688,
    5.343,
    5.071,
    5.02,
    4.963,
    4.829,
    4.757,
    4.683,
    4.422,
    4.35,
    4.66,
    4.733,
    5.171,
    5.186,
    6.063,
    6.667,
    7.293,
    7.431,
    7.237,
    7.178,
    6.72,
    6.66,
    6.511,
    6.522,
    6.9,
    6.96,
    7.522,
    7.622,
    8.38,
    8.9,
    9.5,
    9.514,
    9.113,
    8.808,
    8.471,
    8.438,
    8.183,
    8.423,
    8.633,
    8.743,
    8.838,
    8.889,
    8.764,
    8.675,
    8.48,
    8.786,
    9.13,
    9.06,
    9.212,
    9.282,
    9.163,
    9.35,
    9.225,
    8.825,
    8.6,
    8.543,
    8.32,
    8.167
  ],
  "watts": [
    168.6745149999994,
    112.44972166666626,
    63.25302750000015,
    2215.144995942778,
    461.9927201580001,
    479.6698829879998,
    428.1676715641048,
    419.6196433559553,
    281.7674962149547,
    168.89091768674504,
    151.808790559545,
    184.25170042376377,
    309.1971444180608,
    261.14489448863645,
    284.6503168300004,
    252.43209282878487,
    215.4019385818,
    262.8459280943948,
    410.424203387795,
    509.5607271680662,
    349.67562401288865,
    269.45199282977774,
    109.52880298127155,
    166.45225960293368,
    151.65110115981835,
    183.20961764922873,
    147.02737590637315,
    161.88424313463543,
    226.89666542393343,
    236.50412365400015,
    225.17419540714536,
    236.767979314615,
    160.3340329488842,
    130.06662829666672,
    161.04493440496017,
    157.20360872459992,
    191.2538281980515,
    515.6831950674797,
    200.7391476556001,
    210.6603681350002,
    210.3183099278449,
    158.73778001203996,
    169.6410898659083,
    200.59766112900027,
    188.02103068906192,
    212.36168761081063,
    211.29293245903216,
    267.87849314267527,
    278.5215187913733,
    275.3358013200948,
    312.90774801405513,
    246.75765077659975,
    304.44460895999975,
    206.16104130000036,
    75.85798964829239,
    34.92426575820001,
    160.8689577239999,
    270.9695557268951,
    177.71092842904005,
    437.735307710805,
    475.3215182879334,
    257.1689583943943,
    270.8746242387333,
    217.3637960558459,
    240.97534117375488,
    223.9512902596011,
    195.4993068434883,
    192.81863470768,
    190.582309021725,
    198.43911652800003,
    181.01716846663996,
    167.37362409635503,
    158.889775058845,
    157.71820359488004,
    168.2427132602249,
    209.4065494609949,
    165.32464844311997,
    161.663698486295,
    211.52924869811497,
    284.1935742268048,
    190.46783790210569,
    179.446511328355,
    175.55422647560002,
    198.65194733204163,
    218.0841203009473,
    229.6488372533599,
    239.2334992431599,
    253.48021083629504,
    275.75172777133844,
    288.7069558796642,
    298.85576853948,
    304.68965386407854,
    159.9836868541152,
    121.92926374753348,
    86.73979359818188,
    140.37850485680357,
    108.09186618550504,
    188.4374847306001,
    442.7518304382146,
    212.2332395481851,
    398.73989672944464,
    279.39485223104003,
    309.0217816678551,
    215.6567521827199,
    189.79615450939997,
    161.21748195000004,
    156.10235909999997,
    155.37734962236,
    222.9621734246951,
    347.03672117739904,
    906.8066884960008,
    616.8665569918949,
    279.0046581490051,
    351.89583101460005,
    364.6574887337149,
    358.92226771020023,
    396.3974147738181,
    581.354428945145,
    538.6973337795885,
    463.41566118459986,
    277.03298613696006,
    83.957753492445,
    167.1848939676151,
    198.26894632032008,
    214.3436742443995,
    253.83627252343575,
    260.6396185925985,
    247.7326877527334,
    191.19857250217856,
    135.72870261576,
    157.69643553079987,
    162.35311626939534,
    137.57424145629503,
    135.819453749915,
    127.96091998630504,
    124.063422826345,
    139.41950697940007,
    148.5568734607509,
    153.530540496905,
    149.2107762466116,
    117.02725920339998,
    123.12011740959726,
    148.3131314512769,
    150.04461361312008,
    160.07490410286323,
    249.4432966004001,
    272.62161828760526,
    363.57829439459954,
    335.14916606702195,
    135.51260270060038,
    112.235592432,
    112.04920148963998,
    122.60082296653304,
    162.77353458533315,
    199.27149552755537,
    242.60935855527245,
    203.8461448830842,
    164.91447793333327,
    166.63390438562493,
    118.87164226808616,
    138.53092232090742,
    218.3489036149844,
    250.83465118020013,
    181.25792214799975,
    188.85862457966695,
    167.43055437258812,
    162.0539776283734,
    141.67606032627702,
    163.92536694430646,
    145.81462917948,
    166.26357034353373,
    169.00563847384834,
    174.96255795810504,
    161.13624992126677,
    164.7263329087224,
    208.36577581720744,
    159.21409745451473,
    134.46928551454454,
    102.80331230569108,
    71.16749015203999,
    69.9936299272,
    57.264923728000014,
    344.893212952,
    385.027943116,
    423.5943588479997,
    508.52008093200016,
    495.4015427759998,
    283.0580964816789,
    260.8015674657005,
    293.40071705696346,
    366.3559759372544,
    260.1930613819184,
    200.73242089803537,
    136.45540604486973,
    138.30737314345797,
    118.43694625687829,
    149.923422490525,
    168.60280297405495,
    207.60883917888015,
    250.7195354377544,
    184.558481410995,
    205.63377609928023,
    352.5528230196,
    230.9283432949733,
    236.17907030248537,
    295.6462094547999,
    307.75688546499964,
    281.89576597378533,
    230.574789191455,
    235.65791559048077,
    215.76897326788503,
    211.7196886498,
    311.85416208062276,
    398.06402452245413,
    329.82748690279993,
    232.38234672784608,
    138.78786002760498,
    130.36895079649497,
    133.81378152607402,
    182.3013744734401,
    186.73982354205793,
    172.20177637301157,
    192.5009051253331,
    209.0475477603449,
    179.425316501525,
    221.9355286361452,
    284.4902160636853,
    271.8077334151953,
    369.3704549253995,
    257.8020785658182,
    192.819333935345,
    148.20717907563505,
    84.13401280571513,
    104.11261665419988,
    89.61181635995393,
    109.5034856126052,
    127.6684497346,
    94.09888400800016,
    72.32060931115512,
    95.3440176828222,
    68.63012357644443,
    101.49662337379569,
    115.03000479947389,
    96.88718158932949,
    123.72855952899998,
    184.3545479766667,
    140.84747388441602,
    130.3400171091817,
    143.7965334481981,
    131.0503554647466,
    170.0538634156001,
    157.58472421789492,
    127.62087724358172,
    149.64531085885503,
    143.64216704805062,
    175.61501723132463,
    258.5096182722667,
    227.48314077162536,
    264.90110852330355,
    290.3773391214,
    188.63472166322236,
    206.99781368081193,
    86.18914883118505,
    300.2818638577999,
    140.2305606239999,
    159.43463553151506,
    474.05048377155487,
    233.59549704826543,
    258.43788489547944,
    409.26014158592005,
    262.1782947574002,
    235.2733787488752,
    296.17077683827296,
    254.89394580036395,
    196.20078293233317,
    223.55838116500033,
    200.3891773009754,
    139.06983048706675,
    136.30634603420515,
    216.48974507293337,
    154.11685535,
    110.78220294752003,
    150.98115359627997,
    228.0995677012666,
    206.5112456376774,
    244.22046355500007,
    356.38876008800077,
    204.73329771372823,
    95.5704920934,
    92.93516928636,
    138.92961935915517,
    182.74920648931487,
    196.2304779169151,
    308.26204799819993,
    204.60652272299993,
    130.76311653500005,
    168.95903216199997,
    133.91318910400005,
    344.23357633199987,
    332.65369720399974,
    216.2960423056932,
    221.5714699978426,
    203.43889410275725,
    195.7288854571095,
    205.8890908855444,
    209.40110866080863,
    204.4371484813659,
    197.946310937195,
    197.29537076262855,
    204.7605219937551,
    235.58234250507047,
    310.9207027673846,
    300.39121474290926,
    278.6062443174784,
    204.7804299479469,
    83.675639739995,
    79.48855339054501,
    78.69057840340001,
    78.415826923,
    206.341400894355,
    301.2213572605999,
    292.6346833240001,
    206.01063743966623,
    147.50962095934477,
    156.26493576399008,
    157.1185145806669,
    205.95176578014275,
    290.647394514,
    149.49811597199997,
    184.5390128406451,
    220.35543210739985,
    283.3543266251255,
    212.8251719769998,
    292.63687041964,
    308.5494268215548,
    209.74238945048,
    209.64961854148,
    289.63242785294455,
    264.81853093576,
    298.9498949684547,
    254.29586145260023,
    387.3595278959997,
    247.05596709500003,
    222.11359770436,
    214.063443464145,
    205.66173525832005,
    188.49001695240003,
    172.972785772645,
    171.42068952340003,
    224.45039639628448,
    161.56012798580002,
    391.7356965079982,
    199.1881331279993,
    225.8678834309987,
    163.64621627400004,
    343.58939536799943,
    449.4270058680007,
    568.7615833279987,
    603.4039231680003,
    618.4767501720007,
    814.6487592199993,
    770.5232644360001,
    765.9124174360005,
    695.7640273879994,
    546.6017934051458,
    644.5035366650403,
    1009.9397366531988,
    749.6778012616047,
    1151.2435232546,
    653.339549700001,
    518.5190599573551,
    499.0385344006,
    485.15544302728506,
    629.3450920097997,
    870.6739965967272,
    1013.7808263360002,
    795.804003368,
    604.1497474188287,
    354.7834864134003,
    307.562753750145,
    296.09538138011465,
    357.68277101332484,
    388.2105947540148,
    217.64189507419985,
    280.39844278400034,
    291.167596312,
    299.2569782547436,
    238.96214616459983,
    120.647168446145,
    127.55888592143388,
    115.5489422394,
    99.93860055527166,
    120.60179856647194,
    71.63169422206651,
    97.7188398813953,
    96.84047664851116,
    133.68172305866665,
    123.06136656704008,
    121.53120633580932,
    156.3578837925998,
    111.9356161421222,
    135.6579824046424,
    133.24806369470627,
    166.329603476467,
    142.98845810764027,
    165.10686746972175,
    112.17977889348889,
    86.64402411746816,
    113.20442914131714,
    96.92138872206668,
    77.24369031515185,
    133.55858616341533,
    91.36042219378712,
    81.56494915463388,
    100.94270083778684,
    177.8151992417334,
    341.91898960439505,
    184.32992945951983,
    157.0345212163999,
    145.6425493270003,
    147.8138340584784,
    239.59437045851067,
    257.7499678023948,
    277.6945854925115,
    130.08577325736334,
    126.87000930882402,
    157.15978647633943,
    147.9399148490363,
    174.05909310848006,
    312.54224287046986,
    402.9689952556182,
    292.9792300407998,
    260.6650696612376,
    107.50577227550502,
    159.58836917459968,
    119.96856725398442,
    202.3408174480286,
    379.9858604693994,
    313.11740135039486,
    331.3981995710401,
    246.8385453893111,
    247.41454744534497,
    232.66627534954537,
    195.05454015793276,
    162.82024373187514,
    135.34766755800035,
    111.62020170276944,
    104.47497787480496,
    290.1357917106004,
    220.6672725916401,
    111.4646725702,
    104.92127304599998,
    163.01932980973717,
    136.61439630256018,
    166.53438477280022,
    209.39068316914523,
    239.79123494540008,
    222.82042256128273,
    193.41935933129324,
    167.43279126997402,
    137.4060962163449,
    120.35378394522688,
    159.09840107965334,
    186.8551756273596,
    197.57315992920095,
    197.0405724797597,
    162.13610862657166,
    182.60208979328831,
    204.4904239246,
    203.5798945316452,
    161.34953205232307,
    170.32045533261558,
    142.23045415866633,
    163.91849506566726,
    196.18584839814497,
    179.76459877576028,
    137.5834943522853,
    57.95921839246607,
    29.133842067895,
    36.25473670571163,
    28.624579194545,
    28.192130885555,
    58.09093885659997,
    35.6879628896401,
    83.95657688119991,
    30.523476464,
    87.28266355066133,
    191.1181130866005,
    127.3914655293337,
    88.71536209377786,
    40.845973741645,
    49.014705155400165,
    81.69286276800004,
    48.7426830119999,
    155.18762744400047,
    169.9200626759999,
    257.1354269440002,
    337.66628360000004,
    331.8101134440244,
    254.65826218959285,
    266.6251334639554,
    172.95114474734208,
    112.7134493508399,
    172.23282508551472,
    277.97259952334474,
    305.74658738103176,
    220.79185070978463,
    269.6485689218006,
    192.1697745534952,
    175.28407136535247,
    163.3023215900002,
    179.37104326997212,
    164.29846677069793,
    158.71271228789325,
    181.38165944598185,
    129.17207119755608,
    134.3947315563531,
    181.2011785653425,
    205.16926540351568,
    143.07263346761002,
    133.86564792399955,
    76.04625513471501,
    89.48683526132572,
    164.14807075486664,
    430.6012243284785,
    525.7975215194001,
    371.7654803106665,
    303.4205957648559,
    552.5415550866002,
    396.27690413563727,
    372.9373540951,
    233.17632365660003,
    228.66862985600005,
    224.86890193100004,
    224.23090774200008,
    224.2140403040001,
    302.264804103855,
    436.2197146746,
    366.0156870913452,
    303.7094528552802,
    395.7770793457049,
    410.6204743079336,
    391.9024388649591,
    595.6673043168003,
    343.610689005845,
    328.06895357940004,
    345.1543043439997,
    456.7356028561063,
    665.1753980065998,
    570.1979329719995,
    468.8783105080006,
    373.097398407895,
    363.945836661755,
    361.62290382172,
    357.56435656529504,
    340.8433501054,
    345.29173345033695,
    329.80625055422325,
    305.78711510000005,
    286.7199139777777,
    245.728492495355,
    239.7518064206,
    223.33875197764,
    219.22472550024003,
    201.241675610845,
    372.9494136182548,
    607.0057487646009,
    370.65733459200015,
    248.799093156,
    238.76981252400003,
    235.76169707499997,
    227.70135268999996,
    208.14975315600003,
    205.69804333414496,
    202.43531339475504,
    210.5086046232666,
    199.963485006605,
    193.330062479815,
    186.34101710248,
    181.9572653486,
    335.25508798200025,
    268.721649423126,
    278.7838311419596,
    747.9278682528004,
    370.1051619698942,
    584.7986917133999,
    540.4195126439997,
    510.04972435200017,
    598.1825816999998,
    574.9367214040008,
    427.9083344640002,
    414.7689633039995,
    285.343317348,
    245.226483308,
    213.609838876,
    309.0206988988545,
    283.2797362885998,
    289.5257922531052,
    363.6213531826004,
    669.137590048,
    1082.1657493559994,
    1334.9894709524456,
    814.3346075239999,
    202.609313076,
    165.70355240400002,
    144.68299534000002,
    140.755551536355,
    353.01991518613863,
    287.7642029082105,
    240.1641228170091,
    218.23211381674503,
    114.38312034281584,
    108.80506826059992,
    170.9260131542799,
    128.99064684672675,
    99.70239702147272,
    74.19970767309086,
    57.55880433620835,
    57.00875349863576,
    79.27846214152024,
    84.1390400939075,
    122.76871182884,
    101.09841447556008,
    88.85627189086533,
    88.34186868326667,
    96.52851282533337,
    85.92627727231657,
    133.64060881336206,
    203.80496271811768,
    220.83443334374417,
    277.4958322667996,
    269.3654455284179,
    237.3587563770665,
    269.78579569125645,
    226.0294835932823,
    244.99573151699968,
    149.63769134199998,
    119.98405377588888,
    140.69610197471644,
    175.97686317670525,
    265.4628952905998,
    198.22644107200017,
    213.431734748,
    200.2232758379489,
    159.3803529306673,
    159.62937762727256,
    37.330068965,
    49.216880953039315,
    71.66269512719956,
    145.40479304199977,
    134.93265227201462,
    152.29047159927754,
    266.9958617359998,
    230.189911548,
    296.95103408436097,
    352.66738591705536,
    228.4531966366,
    169.99830531866627,
    293.1320140999991,
    182.9314650359995,
    147.2137721160012,
    264.9279955008892,
    189.58866485781775,
    153.33239105600023,
    158.45720708399966,
    148.6958163474588,
    172.3817461555856,
    171.01522258859927,
    163.480181124889,
    125.94890128571431,
    127.96969435056438,
    172.46430234060549,
    149.5882749546005,
    143.17515465686245,
    144.30751805647043,
    152.7341170201052,
    184.7824478090918,
    210.79450145560017,
    173.7629962853336,
    158.1091245958815,
    133.41442064019998,
    178.88160679241503,
    707.3399529985945,
    178.4571217381554,
    325.2345737306,
    518.3672663640008,
    299.23938554399933,
    421.64545760533355,
    220.44589366460505,
    206.40749036711497,
    229.98251161008503,
    520.4502542857992,
    301.6489377381199,
    479.3678836884,
    367.9977090280015,
    337.66922399733375,
    445.2960410368212,
    527.9486459293628,
    492.38304848949576,
    367.24916397739986,
    341.30189337697334,
    226.27186728334485,
    229.5495630004795,
    179.4975602176442,
    152.7390512133357,
    285.6349472010937,
    302.0374294493335,
    224.12351992079775,
    201.1077475075524,
    117.20877877088188,
    140.93119982320013,
    307.3754353342144,
    214.69061313520032,
    180.87724492908075,
    481.216763926995,
    412.9016443613991,
    224.02753950000047,
    337.5461216519998,
    295.1134542681444,
    372.8155433994009,
    595.7960920720002,
    597.6890204559998,
    334.88667272800103,
    352.16181185999983,
    290.36921086800004,
    297.6428621736449,
    287.6773448114,
    272.39682323328503,
    344.0745493285558,
    302.5173949546146,
    269.707512756995,
    263.762624933295,
    251.3719786214,
    355.9636229810266,
    522.3889609427999,
    661.9684789640017,
    386.37548895739354,
    379.4927023053999,
    319.37499751999997,
    401.3901347728955,
    464.3805188240668,
    440.2633107159993,
    583.3582781120001,
    411.5445147719998,
    466.8233604191552,
    450.6977769088727,
    367.663534236105,
    343.8830761666,
    391.088513176001,
    337.57933757215505,
    318.4703631206,
    306.144083884,
    301.96058621199995,
    301.85938158399995,
    301.409094746895,
    311.58643435039966,
    348.5787419616404,
    398.50384123619995,
    599.4458309743939,
    378.946938922556,
    407.5257917196398,
    521.8414945671999,
    519.0669292676448,
    585.5274580657452,
    575.5741501367332,
    446.904323612,
    406.17225606822814,
    396.6601994243977,
    284.4464654205057,
    239.16767228539993,
    223.70181265866165,
    189.64733008844007,
    177.47150709956003,
    260.57474048888844,
    344.5537803189277,
    302.54193988906695,
    515.9117917873334,
    443.1199972759995,
    456.7359901533332,
    285.244017961145,
    281.34155185139997,
    275.949780392895,
    258.54192359740006,
    236.712434248155,
    231.83503660152004,
    224.96673307140003,
    215.12651451788,
    244.45444226875503,
    222.16260022762663,
    182.0472245068,
    171.97287143032548,
    166.96731362349175,
    155.90898616464017,
    173.44044440841367,
    223.96434719328175,
    184.2677806064727,
    141.07336894846154,
    218.14824237466655,
    145.95782370399988,
    174.52521137833077,
    252.51453946733832,
    162.04937331045716,
    144.20888005449922,
    168.80369023005557,
    133.0120681615998,
    123.32107639137216,
    119.82721284124,
    121.43364410416008,
    129.91518215280013,
    119.58477723136002,
    139.68423360697915,
    231.5880203365948,
    214.31505384540037,
    188.26008281999984,
    277.1398203366935,
    285.3045596807883,
    335.1061493523647,
    308.6441311090266,
    296.98028618418505,
    316.25921475850834,
    268.66721001302665,
    223.21433687013348,
    184.28655164843292,
    107.01300923693324,
    106.75530423130488,
    172.1972281825998,
    150.40285307738128,
    102.86650125308272,
    86.72361774988471,
    115.36734190004238,
    148.21133894046417,
    123.08822957413489,
    104.95632436460014,
    104.40797536200002,
    97.157396060895,
    102.11099873739975,
    145.80008557429346,
    157.5455640658631,
    143.51087469697978,
    141.97486726171866,
    144.4327989537085,
    196.86478069525313,
    179.66365772988468,
    164.04439671941745,
    175.1346810559999,
    159.21605775537506,
    175.89917330400007,
    257.24630509820986,
    100.83286837711998,
    99.1676157004,
    107.33220365215504,
    97.87295283944002,
    122.07958471350386,
    166.79150825351115,
    214.1093006292451,
    210.22646348540005,
    280.26676689860005,
    143.61389988370073,
    129.68709257928,
    169.1219591957578,
    201.62177970244488,
    139.737762783285,
    133.635915617675,
    132.472990755,
    132.00865511311997,
    131.25217169700502,
    199.63141710271833,
    191.14947506704144,
    313.92672318563615,
    202.7067756588587,
    185.75794319388,
    190.7034354362658,
    184.06165246312509,
    174.41078379163065,
    214.6779729604001,
    154.100102052755,
    136.39327967295998,
    146.7226829976451,
    185.31437828340032,
    151.68200899763949,
    206.5394682013252,
    250.07090602442167,
    311.98188405659965,
    325.1541405236817,
    285.0339393784451,
    241.8981239953999,
    348.7081260023951,
    281.1830633846449,
    260.7760661071776,
    179.13646002666673,
    102.77197584,
    125.46688635949526,
    138.979419602095,
    144.46884596734762,
    182.8039012205591,
    176.63365097499997,
    185.46641584300025,
    202.26258586692023,
    213.06164746209816,
    200.97536627577404,
    163.05274649554826,
    150.83529510540825,
    155.72664460178493,
    138.3885434631332,
    185.05156371187485,
    127.37558139900057,
    124.71669829999988,
    123.15787099885712,
    162.8751799018809,
    113.81819274384502,
    113.43169150035996,
    169.34146543235607,
    244.02623910380495,
    290.57258449143274,
    216.36665896593348,
    201.8804825826666,
    193.568289852355,
    153.11651722020616,
    192.64066356439977,
    253.39504504165777,
    169.03654030428422,
    179.1491716416934,
    129.03267422031524,
    209.7073941782001,
    238.65363822191256,
    148.79870947954535,
    156.07173156402877,
    109.84676119793332,
    149.26521655066566,
    213.71974519005173,
    143.7939723468,
    121.56745260391288,
    74.281036895625,
    89.12381935200891,
    108.46382777720486,
    86.26384612294858,
    197.24561800728023,
    198.30370416159977,
    163.30810535451508,
    171.25505846389098,
    194.67313237035273,
    160.66356974851772,
    143.19182878537333,
    197.5733396565948,
    142.00456440976006,
    91.71303172491996,
    91.207960926115,
    88.96221291324,
    102.2502941941566,
    183.4214122441884,
    211.19040756106665,
    199.2435823802681,
    118.3399837934,
    136.23934959815358,
    126.1369117065885,
    164.73901669529403,
    201.2929346614561,
    215.5438081675203,
    189.20995183940605,
    193.725886282255,
    158.17078853771991,
    154.8130763367599,
    150.05712569134812,
    188.6044868035951,
    116.55150626534775,
    51.89050484039988,
    46.77627082600008,
    18.602163203719996,
    18.157513721239997,
    71.72216422531504,
    81.78365416114154,
    120.6606970492884,
    141.9980349345953,
    104.81686905387151,
    127.64134859017848,
    134.85164529257432,
    188.19524271730265,
    150.4608677439993,
    148.55764320400016,
    120.362397384,
    125.93003421866666,
    126.19934527636003,
    125.05506370501485,
    158.83073431520037,
    237.92644535533353,
    241.3146346846452,
    264.6446219860671,
    262.82722177015364,
    248.90076796639465,
    286.67902057893866,
    255.8527241076397,
    234.52931384428652,
    259.97794730972504,
    220.5553581819321,
    181.1659587000853,
    278.58104697226116,
    214.23711429095144,
    212.0681141725852,
    126.65391355379738,
    156.86689838705558,
    148.68889435434534,
    149.55100675539953,
    230.45789353810548,
    169.4788654174955,
    203.30854484712864,
    260.4148987494005,
    161.55524938035987,
    164.5074284443478,
    200.95789574568275,
    163.6784434475028,
    155.16295438229068,
    174.8669240352282,
    171.51438350926168,
    153.7006329537213,
    166.22428047214842,
    167.30967813681266,
    142.3147438168494,
    189.54231218993365,
    132.03371335473298,
    160.98751496329072,
    166.5188635797453,
    188.86247565007412,
    220.44170311342472,
    192.27897713700017,
    203.11069485699977,
    159.51702112078914,
    113.16865231970678,
    97.66991127672172,
    108.37495023914512,
    132.63545613300536,
    95.34010123212173,
    145.88553156115776,
    144.79596656558985,
    188.51193107549568,
    149.6268906897998,
    171.58887114266636,
    147.07110279370627,
    162.67062515621126,
    162.99749190943663,
    177.70618707258228,
    144.56031140680048,
    153.9396725060119,
    168.4915329840247,
    150.25565312812,
    130.3506093451847,
    169.85764666813333,
    239.73845042910528,
    257.1021647074457,
    44.74281585274952,
    64.11144857144316,
    57.702982409117425,
    34.755799839414045,
    25.91657865504448,
    0.4332352312,
    426.3464057854,
    138.65170543297324,
    250.8449711172614,
    246.9361507893381,
    188.5338435922785,
    245.37376246139985,
    304.9453400039998,
    231.42922458537527,
    594.3250770830001,
    407.8067862893547,
    341.9198228909605,
    649.0655594229052,
    778.3686568386,
    639.33958706,
    626.8114478441444,
    1039.1324247594016,
    916.8379520399995,
    814.6017978918546,
    1270.3745813205994,
    1069.8916131520004,
    920.5972604999996,
    650.3127330973962,
    933.6833663333996,
    829.0813883120015,
    782.4642513119975,
    664.442258984,
    680.8375756679998,
    665.8684560413952,
    665.407198040615,
    653.2351953462003,
    647.1932868571051,
    677.2349002701549,
    613.7871865279999,
    542.221108756,
    486.708550652,
    472.6058828978949,
    463.227526010615,
    421.242495897095,
    387.7304665814,
    379.40726481199994,
    379.011489141355,
    361.594397225245,
    378.393512180005,
    468.4986766582402,
    543.5760190557457,
    523.2056189734552,
    512.9617978960005,
    545.6624289858771,
    432.9872998679548,
    337.75403152993306,
    269.408274812,
    152.21537558765525,
    176.4557416622593,
    147.40773119441312,
    144.12946129939223,
    130.168668451378,
    98.16573604340034,
    127.740096193155,
    58.158611662224885,
    70.19907279100006,
    89.46472986846474,
    118.8539085068478,
    197.4776251273272,
    226.536652224,
    223.28815442710496,
    203.32798757689136,
    229.60680409833293,
    298.05280118334497,
    194.04750376949303,
    201.71286618979968,
    222.5140672516887,
    213.79221617471,
    197.57288448824025,
    191.76025091780593,
    136.21240848578117,
    75.46817862599983,
    54.593679447999776,
    77.28529448384477,
    54.732424138426566,
    64.00975071083566,
    91.59888635675986,
    122.78725972929388,
    119.76626078756011,
    116.5781704643641,
    133.51810543698133,
    208.01532035126468,
    166.58602625573366,
    246.02339842656397,
    234.68563755726683,
    129.14745792894126,
    124.973417629125,
    154.8015639050057,
    249.22395185227984,
    172.6207352292784,
    211.0610609918132,
    339.4520068042053,
    325.31219348259947,
    263.6118271930001,
    282.36026827799947,
    309.42052818800016,
    343.73720011189414,
    267.0838911672753,
    403.7715878549999,
    453.0490512880006,
    350.9939283848936,
    503.3488385214002,
    494.69211524800016,
    536.300781423645,
    573.0025603927334,
    381.616232419,
    376.49515833964506,
    364.030173851755,
    367.40692728060014,
    417.9859003294535,
    545.7758622443991,
    477.7127899241052,
    681.3045628829334,
    860.9752015980007,
    691.9661499040003,
    507.1689628188949,
    510.19491850939914,
    655.4323077559998,
    820.473338500105,
    866.9553424106005,
    873.7302510713124,
    896.4786513173372,
    705.5650673297553,
    499.1465803698545,
    229.56290434059952,
    107.69229367005975,
    139.48136347048904,
    135.7415716944,
    136.36806881111656,
    205.12840185605336,
    232.3530743124,
    189.22987223417633,
    183.39146753657832,
    89.80510266481187,
    83.82182358384445,
    73.88629110671636,
    81.08362370626688,
    94.449884117634,
    104.44885874785902,
    129.7978521480802,
    113.90422405459992,
    122.73677625848023,
    108.8315727296,
    122.84973940353176,
    96.53641738092172,
    106.235510715,
    100.38974883124506,
    80.01890708761718,
    89.97147511196692,
    105.05119073632032,
    78.56630172583864,
    69.37356541196226,
    59.246091007581065,
    45.10803584905246,
    48.05446703224697,
    54.25381944869037,
    58.55471945440003,
    123.899321078848,
    155.2310317765594,
    242.8358525934664,
    348.03074118400707,
    174.11262880500044,
    209.373715603651,
    154.64509854793343,
    151.38715737660115,
    267.16863848488487,
    312.1629410213912,
    196.888568810133,
    281.7610757251198,
    154.5345180394005,
    282.0855131099999,
    143.20368975514498,
    190.81164782955796,
    220.33399172044489,
    154.572972687145,
    152.39980445028002,
    151.14413302188004,
    185.70865518874288,
    162.3768419876399,
    180.63283695720037,
    276.35710160711767,
    264.2377816362532,
    311.8041296153997,
    225.86398085533332,
    207.50260760531933,
    207.18900912412033,
    267.2853363653087,
    234.9077541628941,
    127.54191867374442,
    98.28138493939912,
    97.56789231200062,
    136.39867707100086,
    181.8485962476403,
    124.60754896786666,
    82.17254597966706,
    128.1932443656925,
    144.3638019864533,
    231.4820250941154,
    374.39522674980486,
    333.3594629986003,
    434.5510272679998,
    166.5814016240004,
    156.18135901599982,
    178.61880827599992,
    192.63829953200025,
    173.4863816126444,
    235.0598202954002,
    247.1331947200001,
    225.50697725436,
    208.11067086367476,
    266.2962794216666,
    227.83084674188055,
    203.64437074659963,
    230.27896938600017,
    283.3443548522133,
    249.40173363264003,
    346.3004896178445,
    299.24372360340055,
    352.4212266159997,
    308.4567295480002,
    297.07351500789446,
    353.6191911897218,
    524.4113643805989,
    560.0671660750402,
    630.3166458965994,
    588.3971306199992,
    267.49006609836,
    252.19500280569497,
    209.8638884574,
    185.419014247,
    188.2105678264736,
    190.07966287706944,
    182.41131857506943,
    194.2783535296992,
    229.44107189839983,
    256.83857047239474,
    206.36909681200424,
    285.95769259578464,
    233.540129813334,
    193.0470446043603,
    212.63373500153696,
    174.12896699993345,
    127.37489520363992,
    95.16065301638564,
    48.50306239102886,
    54.40984292209501,
    88.61998298082858,
    100.36047999686276,
    191.04522832980032,
    146.7594839333715,
    154.16405133386644,
    177.84849940635473,
    225.3633976367049,
    434.8237173146001,
    122.45301152199502,
    164.2695505593999,
    189.73636061974497,
    135.870056063915,
    190.2235665683202,
    222.3861336794,
    304.93477080335504,
    259.9096023839754,
    217.66523231633337,
    244.59457941300025,
    166.33786932500024,
    212.50199583010476,
    340.50271115490665,
    205.79371460616065,
    139.25543455680037,
    181.17063897600065,
    82.39822555999984,
    72.33273966057143,
    163.4980551840001,
    351.9523208856051,
    495.9384805626002,
    156.39892945571466,
    127.1098124052,
    125.955970586,
    109.836075372,
    154.4309961400004,
    283.37262442899987,
    230.6592495924949,
    228.2132256372446,
    144.26909837820193,
    130.76374227640008,
    218.03404455599957,
    267.2694876773337,
    147.89496182800002,
    177.83902831510508,
    204.08032228531448,
    261.8789670882002,
    180.00192292902662,
    173.4483650253045,
    205.6367265629601,
    182.79073873880012,
    303.3692605730214,
    424.8539131801291,
    424.54326375600056,
    276.60537116211947,
    159.10088929128037,
    339.86023231759987,
    194.0523713732144,
    280.0787780788719,
    305.14648749060046,
    672.5800355350002,
    417.8024901916556,
    262.25130435372057,
    481.07140346640006,
    451.6821931879997,
    265.32085312399994,
    373.5592046760015,
    405.8719259146443,
    406.1038055754004,
    430.2554878480007,
    322.3916982229095,
    352.84870946514474,
    297.9760221654,
    304.1346160699997,
    353.7980179731884,
    314.47646195860943,
    284.7672419008532,
    335.8254077610665,
    255.90803191013632,
    230.7193464638893,
    181.13852249140052,
    109.8282663757371,
    81.749721244625,
    79.76181914900002,
    190.26130752631556,
    209.74149620679157,
    210.06002076196276,
    190.16685591507996,
    81.4355940376,
    107.85372116328494,
    114.18157507367997,
    88.82322980894502,
    83.27776113527501,
    131.26359539604002,
    216.3906348224944,
    305.20709990533817,
    288.56515154773354,
    262.6374876600004,
    237.48069556436,
    173.8644407260944,
    125.75592436363988,
    64.5515698119849,
    72.48989190379505,
    97.15067023804,
    200.85683876831985,
    318.3257113717333,
    297.969724788,
    198.2658089121448,
    341.56047026140027,
    423.7539436919991,
    272.3748328573946,
    194.80477185602572,
    480.0859280649994,
    189.85427040800005,
    293.5169102426046,
    530.8036825546004,
    455.00528729215495,
    386.9378083016,
    297.30516701665465,
    286.3921731165999,
    282.16638303139496,
    259.9628137054005,
    349.1250833222532,
    421.8367046785446,
    323.776511105005,
    229.77256589459964,
    191.3651992292922,
    152.830828466309,
    138.66112909166657,
    148.91473467419317,
    144.41645595288708,
    141.57159652706733,
    364.61315256600057,
    233.2859620230003,
    230.90452416066736,
    151.8745623853328,
    253.79980825199985,
    95.504015647105,
    93.8643656306,
    92.465318382785,
    221.90640601757175,
    169.37371431925484,
    230.28227024399493,
    180.44759084825725,
    181.90432249499915,
    186.05844781499985,
    341.5086943740007,
    550.0978105439998,
    551.4915210359995,
    344.0367048963602,
    469.8348412218004,
    500.99099279035454,
    490.38132466845536,
    515.2620044366001,
    356.3230487738551,
    331.1007416326,
    313.85391892099494,
    294.6264080364799,
    278.83288294172496,
    255.06558257792005,
    248.75121660732,
    231.03961573336,
    223.631511034675,
    212.57774064188004,
    268.79632308922675,
    299.088078332195,
    288.82521273839984,
    207.253275471014,
    161.92038004631505,
    158.5530380582,
    139.27494183599998,
    150.53522659466694,
    206.72270802328572,
    196.40208409735487,
    297.54441404368015,
    570.3730544795998,
    219.35278829884487,
    264.7958784434004,
    369.4873179799995,
    278.35169518500066,
    388.0045768419995,
    692.8223947480005,
    868.1897411186662,
    426.8796900600002,
    395.5262098026452,
    391.07208885118496,
    432.40023811319577,
    531.2557588373993,
    401.4113186320001,
    528.3913682599996,
    409.4500426400001,
    489.1051394578544,
    734.6268921926005,
    432.883888992,
    427.78233082,
    486.43491240800046,
    516.5408130520007,
    583.9825964399996,
    499.2023520852149,
    774.4337299181998,
    511.10090437199943,
    462.69134342,
    438.3304099280001,
    345.355603504,
    415.02496793200055,
    610.1024637760001,
    369.473828731145,
    661.171969544775,
    465.5577659383553,
    1332.646903100599,
    433.49111676,
    378.839693384,
    345.9549053493334,
    281.7447844731151,
    276.4435112177295,
    198.778374451077,
    149.64743974081227,
    114.81603163348724,
    118.61044002864486,
    90.16817630739988,
    124.59240117927273,
    230.04164969527284,
    120.76197732054824,
    165.4558741595334,
    96.3424300416048,
    12.980410241955,
    67.237587956115,
    11.076730829715,
    1321.036120165095,
    172.3361725372538,
    119.5166152634,
    182.81293647195616,
    93.4023883353817,
    83.36071524162855,
    73.40652924336001,
    59.011855801645,
    101.44028536024211,
    159.92811000275094,
    113.43386279645502,
    115.9940736825496,
    139.0996410676909,
    92.5816793189571,
    81.98484277304857,
    43.267867071000005,
    119.607729348,
    94.92562411200004,
    52.523219602105,
    101.99084999712166,
    343.39185518460033,
    325.6308457796049,
    254.67308029880888,
    244.70934355849093,
    179.83865035199986,
    117.06895824688009,
    196.1184755815999,
    220.04940247539488,
    210.31792346602504,
    216.37167967114507,
    220.0151789704,
    240.567782523,
    224.67882669782915,
    160.7941216551834,
    187.18255782467563,
    120.58999855,
    118.33158430999998,
    150.08417254666682,
    131.9612811489999,
    124.672462496645,
    157.4023523780552,
    165.73236218725214,
    183.10265984957888,
    122.71794885781615,
    143.45447012714283,
    218.834298928125,
    161.8650385240805,
    280.77644890759996,
    237.7549819079997,
    190.35890408815496,
    215.2507212206005,
    163.52814420800004,
    207.84690818370584,
    234.59642269899996,
    245.26835990066667,
    213.57943027247836,
    170.24005365444003,
    140.40047519520007,
    126.14266684633334,
    109.30108012399997,
    126.7279423973332,
    131.33547892099998,
    106.587739626345,
    114.68640404728006,
    132.1894038156002,
    121.92455030400004,
    106.604607064345,
    105.589588116385,
    100.44726190515996,
    95.429798919905,
    99.82843375460004,
    91.534247118585,
    88.47320397467499,
    143.95571345260507,
    95.39562267559998,
    104.77188802954169,
    151.04069298131571,
    192.5762111033014,
    180.16533435997331,
    130.59821683920003,
    119.48359663600009,
    247.90109845405263,
    223.70796577859997,
    198.59937387999992,
    161.27844558363986,
    38.5075168332,
    107.30442266400004,
    17.596102424,
    12.495633678145,
    98.81284296085454,
    77.04013659999995,
    129.07129725570553,
    250.72510404267504,
    271.02788466100003,
    162.6844708933334,
    151.00513978823537,
    93.57249096800004,
    74.18978275709087,
    120.08041101866664,
    96.0108050762602,
    111.70473458639998,
    152.92704549610494,
    99.78777041891372,
    140.55362136318905,
    124.23960768239984,
    90.15542288166245,
    105.79181302671164,
    67.45074182340012,
    107.28363842947178,
    88.06102876131503,
    56.727094243325105,
    79.9951575846782,
    74.19319566620487,
    110.26796539857529,
    158.39957978679996,
    129.04917826736013,
    138.82807224295382,
    174.18650626033332,
    202.0825070471953,
    133.28719934539993,
    87.66979599733334,
    28.82509984,
    27.449938848644997,
    101.06296731940002,
    175.9158737594102,
    284.6988340986071,
    151.4793926637201,
    158.85985708581177,
    123.11763596982745,
    192.33714513072,
    174.13753681974492,
    192.5993026095186,
    202.7736227658,
    153.8236037422452,
    120.49474775979937,
    86.92618152268813,
    45.121460815699486,
    35.464722824479814,
    40.57569212990429,
    90.72575254244448,
    103.64363930030795,
    117.79611051825022,
    79.12355614215973,
    121.29669229461388,
    126.07162559814284,
    167.87719423613723,
    139.56699123728657,
    192.68503006978605,
    158.5795973835199,
    196.9399358123997,
    146.7859420040001,
    135.38249105198489,
    115.5776330869542,
    91.2283222836,
    104.65279642799976,
    125.62970929908002,
    150.44114089667977,
    236.8284350076002,
    253.11134786399992,
    305.0217109199999,
    253.48426048252833,
    302.26205955869517,
    257.4174934049201,
    183.49545672018488,
    109.62702920992,
    102.008060405545,
    130.105915243345,
    154.13285549129478,
    146.92759230374529,
    137.2139951715198,
    134.438105507415,
    156.16074153631385,
    148.2169380472343,
    130.00071358677772,
    196.41232782435975,
    170.82031644437157,
    131.078320882,
    193.97498429087975,
    212.68827229588013,
    160.2727900468451,
    206.90389351106663,
    172.82385273384887,
    153.8988242902842,
    151.92741419326086,
    141.1997302960118,
    106.1941603794,
    101.348974148105
  ],
  "weather_applied": false,
  "wind_rel": [
    -0.0,
    -0.0,
    -0.0,
    -0.0,
    -0.0,
    -0.0,
    -0.0,
    -0.0,
    -0.0,
    -0.0,
    -0.0,
    -0.0,
    -0.0,
    -0.0,
    -0.0,
    -0.0,
    -0.0,
    -0.0,
    -0.0,
    -0.0,
    -0.0,
    -0.0,
    -0.0,
    -0.0,
    -0.0,
    -0.0,
    -0.0,
    -0.0,
    -0.0,
    -0.0,
    -0.0,
    -0.0,
    -0.0,
    -0.0,
    -0.0,
    -0.0,
    -0.0,
    -0.0,
    -0.0,
    -0.0,
    -0.0,
    -0.0,
    -0.0,
    -0.0,
    -0.0,
    -0.0,
    -0.0,
    -0.0,
    -0.0,
    -0.0,
    -0.0,
    -0.0,
    -0.0,
    -0.0,
    -0.0,
    -0.0,
    -0.0,
    -0.0,
    -0.0,
    -0.0,
    -0.0,
    -0.0,
    -0.0,
    -0.0,
    -0.0,
    -0.0,
    -0.0,
    -0.0,
    -0.0,
    -0.0,
    -0.0,
    -0.0,
    -0.0,
    -0.0,
    -0.0,
    -0.0,
    -0.0,
    -0.0,
    -0.0,
    -0.0,
    -0.0,
    -0.0,
    -0.0,
    -0.0,
    -0.0,
    -0.0,
    -0.0,
    -0.0,
    -0.0,
    -0.0,
    -0.0,
    -0.0,
    -0.0,
    -0.0,
    -0.0,
    -0.0,
    -0.0,
    -0.0,
    -0.0,
    -0.0,
    -0.0,
    -0.0,
    -0.0,
    -0.0,
    -0.0,
    -0.0,
    -0.0,
    -0.0,
    -0.0,
    -0.0,
    -0.0,
    -0.0,
    -0.0,
    -0.0,
    -0.0,
    -0.0,
    -0.0,
    -0.0,
    -0.0,
    -0.0,
    -0.0,
    -0.0,
    -0.0,
    -0.0,
    -0.0,
    -0.0,
    -0.0,
    -0.0,
    -0.0,
    -0.0,
    -0.0,
    -0.0,
    -0.0,
    -0.0,
    -0.0,
    -0.0,
    -0.0,
    -0.0,
    -0.0,
    -0.0,
    -0.0,
    -0.0,
    -0.0,
    -0.0,
    -0.0,
    -0.0,
    -0.0,
    -0.0,
    -0.0,
    -0.0,
    -0.0,
    -0.0,
    -0.0,
    -0.0,
    -0.0,
    -0.0,
    -0.0,
    0.0,
    0.0,
    0.0,
    0.0,
    0.0,
    0.0,
    0.0,
    0.0,
    0.0,
    0.0,
    0.0,
    0.0,
    0.0,
    0.0,
    0.0,
    0.0,
    0.0,
    0.0,
    0.0,
    0.0,
    0.0,
    0.0,
    0.0,
    0.0,
    0.0,
    0.0,
    0.0,
    0.0,
    0.0,
    0.0,
    0.0,
    0.0,
    0.0,
    0.0,
    0.0,
    0.0,
    0.0,
    0.0,
    0.0,
    -0.0,
    -0.0,
    -0.0,
    -0.0,
    -0.0,
    -0.0,
    -0.0,
    -0.0,
    -0.0,
    -0.0,
    -0.0,
    -0.0,
    -0.0,
    -0.0,
    -0.0,
    0.0,
    0.0,
    0.0,
    0.0,
    0.0,
    0.0,
    0.0,
    0.0,
    0.0,
    0.0,
    0.0,
    0.0,
    0.0,
    0.0,
    0.0,
    0.0,
    0.0,
    0.0,
    0.0,
    0.0,
    -0.0,
    -0.0,
    -0.0,
    -0.0,
    -0.0,
    -0.0,
    -0.0,
    -0.0,
    -0.0,
    -0.0,
    -0.0,
    -0.0,
    -0.0,
    -0.0,
    -0.0,
    -0.0,
    -0.0,
    -0.0,
    -0.0,
    -0.0,
    -0.0,
    -0.0,
    -0.0,
    -0.0,
    -0.0,
    -0.0,
    -0.0,
    -0.0,
    -0.0,
    -0.0,
    -0.0,
    -0.0,
    -0.0,
    -0.0,
    -0.0,
    -0.0,
    -0.0,
    -0.0,
    -0.0,
    -0.0,
    -0.0,
    -0.0,
    -0.0,
    -0.0,
    -0.0,
    -0.0,
    -0.0,
    -0.0,
    -0.0,
    -0.0,
    -0.0,
    -0.0,
    -0.0,
    -0.0,
    -0.0,
    -0.0,
    -0.0,
    -0.0,
    -0.0,
    -0.0,
    -0.0,
    -0.0,
    -0.0,
    -0.0,
    -0.0,
    -0.0,
    -0.0,
    -0.0,
    -0.0,
    -0.0,
    -0.0,
    -0.0,
    -0.0,
    -0.0,
    -0.0,
    -0.0,
    -0.0,
    -0.0,
    0.0,
    0.0,
    0.0,
    0.0,
    0.0,
    -0.0,
    -0.0,
    -0.0,
    -0.0,
    -0.0,
    -0.0,
    -0.0,
    -0.0,
    -0.0,
    -0.0,
    -0.0,
    -0.0,
    -0.0,
    -0.0,
    -0.0,
    -0.0,
    -0.0,
    -0.0,
    -0.0,
    -0.0,
    -0.0,
    -0.0,
    -0.0,
    -0.0,
    -0.0,
    -0.0,
    -0.0,
    -0.0,
    -0.0,
    -0.0,
    0.0,
    0.0,
    -0.0,
    -0.0,
    -0.0,
    -0.0,
    -0.0,
    0.0,
    0.0,
    0.0,
    0.0,
    0.0,
    0.0,
    0.0,
    0.0,
    0.0,
    0.0,
    0.0,
    0.0,
    0.0,
    0.0,
    0.0,
    0.0,
    0.0,
    0.0,
    0.0,
    0.0,
    0.0,
    0.0,
    0.0,
    0.0,
    0.0,
    0.0,
    0.0,
    0.0,
    0.0,
    0.0,
    0.0,
    0.0,
    0.0,
    0.0,
    0.0,
    0.0,
    0.0,
    0.0,
    0.0,
    0.0,
    0.0,
    0.0,
    0.0,
    0.0,
    0.0,
    0.0,
    0.0,
    0.0,
    0.0,
    0.0,
    0.0,
    0.0,
    0.0,
    0.0,
    0.0,
    0.0,
    0.0,
    0.0,
    0.0,
    0.0,
    0.0,
    0.0,
    0.0,
    0.0,
    0.0,
    0.0,
    0.0,
    0.0,
    0.0,
    0.0,
    0.0,
    0.0,
    0.0,
    0.0,
    0.0,
    0.0,
    0.0,
    0.0,
    0.0,
    0.0,
    0.0,
    0.0,
    0.0,
    0.0,
    0.0,
    0.0,
    0.0,
    0.0,
    0.0,
    0.0,
    0.0,
    0.0,
    0.0,
    0.0,
    0.0,
    0.0,
    0.0,
    0.0,
    0.0,
    0.0,
    0.0,
    0.0,
    0.0,
    0.0,
    -0.0,
    -0.0,
    -0.0,
    -0.0,
    -0.0,
    -0.0,
    -0.0,
    -0.0,
    -0.0,
    -0.0,
    -0.0,
    -0.0,
    -0.0,
    -0.0,
    -0.0,
    -0.0,
    -0.0,
    -0.0,
    -0.0,
    -0.0,
    -0.0,
    -0.0,
    -0.0,
    -0.0,
    -0.0,
    -0.0,
    -0.0,
    -0.0,
    -0.0,
    -0.0,
    -0.0,
    -0.0,
    -0.0,
    0.0,
    0.0,
    0.0,
    0.0,
    0.0,
    0.0,
    0.0,
    0.0,
    0.0,
    0.0,
    0.0,
    0.0,
    0.0,
    0.0,
    0.0,
    0.0,
    0.0,
    0.0,
    0.0,
    0.0,
    0.0,
    0.0,
    0.0,
    0.0,
    0.0,
    0.0,
    0.0,
    0.0,
    0.0,
    0.0,
    0.0,
    0.0,
    0.0,
    0.0,
    0.0,
    0.0,
    0.0,
    0.0,
    0.0,
    0.0,
    0.0,
    0.0,
    0.0,
    0.0,
    0.0,
    0.0,
    0.0,
    0.0,
    0.0,
    0.0,
    0.0,
    0.0,
    0.0,
    0.0,
    0.0,
    0.0,
    0.0,
    0.0,
    0.0,
    0.0,
    0.0,
    0.0,
    0.0,
    0.0,
    0.0,
    0.0,
    0.0,
    0.0,
    0.0,
    0.0,
    0.0,
    0.0,
    0.0,
    0.0,
    0.0,
    0.0,
    0.0,
    0.0,
    0.0,
    0.0,
    0.0,
    0.0,
    0.0,
    0.0,
    0.0,
    0.0,
    -0.0,
    -0.0,
    -0.0,
    -0.0,
    -0.0,
    -0.0,
    -0.0,
    -0.0,
    0.0,
    0.0,
    0.0,
    0.0,
    0.0,
    0.0,
    0.0,
    0.0,
    0.0,
    0.0,
    0.0,
    -0.0,
    -0.0,
    -0.0,
    -0.0,
    -0.0,
    -0.0,
    -0.0,
    -0.0,
    -0.0,
    -0.0,
    -0.0,
    -0.0,
    -0.0,
    -0.0,
    -0.0,
    -0.0,
    -0.0,
    -0.0,
    -0.0,
    -0.0,
    -0.0,
    -0.0,
    -0.0,
    -0.0,
    -0.0,
    -0.0,
    -0.0,
    -0.0,
    -0.0,
    -0.0,
    -0.0,
    -0.0,
    -0.0,
    -0.0,
    -0.0,
    -0.0,
    -0.0,
    -0.0,
    -0.0,
    -0.0,
    -0.0,
    -0.0,
    -0.0,
    -0.0,
    -0.0,
    -0.0,
    -0.0,
    -0.0,
    -0.0,
    -0.0,
    -0.0,
    -0.0,
    -0.0,
    -0.0,
    -0.0,
    -0.0,
    -0.0,
    -0.0,
    -0.0,
    -0.0,
    -0.0,
    -0.0,
    -0.0,
    0.0,
    0.0,
    0.0,
    0.0,
    0.0,
    0.0,
    0.0,
    0.0,
    0.0,
    0.0,
    0.0,
    0.0,
    0.0,
    0.0,
    0.0,
    0.0,
    0.0,
    -0.0,
    -0.0,
    -0.0,
    -0.0,
    -0.0,
    -0.0,
    -0.0,
    -0.0,
    -0.0,
    -0.0,
    -0.0,
    -0.0,
    -0.0,
    -0.0,
    -0.0,
    -0.0,
    -0.0,
    -0.0,
    -0.0,
    -0.0,
    -0.0,
    -0.0,
    -0.0,
    -0.0,
    -0.0,
    -0.0,
    -0.0,
    -0.0,
    -0.0,
    -0.0,
    -0.0,
    -0.0,
    -0.0,
    -0.0,
    -0.0,
    -0.0,
    -0.0,
    -0.0,
    -0.0,
    -0.0,
    -0.0,
    -0.0,
    -0.0,
    -0.0,
    -0.0,
    -0.0,
    -0.0,
    -0.0,
    -0.0,
    -0.0,
    -0.0,
    -0.0,
    -0.0,
    -0.0,
    -0.0,
    -0.0,
    -0.0,
    -0.0,
    -0.0,
    -0.0,
    -0.0,
    -0.0,
    -0.0,
    -0.0,
    -0.0,
    -0.0,
    -0.0,
    -0.0,
    -0.0,
    -0.0,
    -0.0,
    -0.0,
    -0.0,
    -0.0,
    -0.0,
    -0.0,
    -0.0,
    -0.0,
    -0.0,
    -0.0,
    -0.0,
    -0.0,
    -0.0,
    -0.0,
    -0.0,
    -0.0,
    -0.0,
    -0.0,
    -0.0,
    -0.0,
    -0.0,
    -0.0,
    -0.0,
    -0.0,
    -0.0,
    -0.0,
    -0.0,
    -0.0,
    -0.0,
    -0.0,
    -0.0,
    -0.0,
    -0.0,
    -0.0,
    -0.0,
    -0.0,
    -0.0,
    -0.0,
    -0.0,
    -0.0,
    -0.0,
    -0.0,
    -0.0,
    -0.0,
    -0.0,
    -0.0,
    -0.0,
    -0.0,
    0.0,
    0.0,
    0.0,
    0.0,
    0.0,
    0.0,
    0.0,
    0.0,
    0.0,
    0.0,
    0.0,
    0.0,
    0.0,
    0.0,
    0.0,
    0.0,
    0.0,
    0.0,
    0.0,
    0.0,
    0.0,
    0.0,
    0.0,
    0.0,
    0.0,
    0.0,
    0.0,
    0.0,
    0.0,
    0.0,
    0.0,
    0.0,
    0.0,
    0.0,
    0.0,
    0.0,
    0.0,
    0.0,
    0.0,
    0.0,
    0.0,
    0.0,
    0.0,
    0.0,
    0.0,
    0.0,
    0.0,
    0.0,
    0.0,
    0.0,
    0.0,
    0.0,
    0.0,
    0.0,
    0.0,
    0.0,
    0.0,
    0.0,
    0.0,
    0.0,
    0.0,
    0.0,
    0.0,
    0.0,
    0.0,
    0.0,
    0.0,
    0.0,
    0.0,
    0.0,
    0.0,
    0.0,
    0.0,
    0.0,
    0.0,
    0.0,
    0.0,
    0.0,
    0.0,
    0.0,
    0.0,
    0.0,
    0.0,
    0.0,
    0.0,
    0.0,
    0.0,
    0.0,
    0.0,
    0.0,
    0.0,
    0.0,
    0.0,
    0.0,
    0.0,
    0.0,
    0.0,
    0.0,
    0.0,
    0.0,
    0.0,
    0.0,
    0.0,
    0.0,
    0.0,
    0.0,
    0.0,
    0.0,
    0.0,
    0.0,
    0.0,
    0.0,
    0.0,
    0.0,
    0.0,
    0.0,
    0.0,
    0.0,
    0.0,
    0.0,
    0.0,
    0.0,
    0.0,
    -0.0,
    0.0,
    0.0,
    0.0,
    0.0,
    0.0,
    0.0,
    0.0,
    0.0,
    0.0,
    0.0,
    0.0,
    0.0,
    0.0,
    0.0,
    0.0,
    0.0,
    0.0,
    0.0,
    0.0,
    0.0,
    0.0,
    0.0,
    0.0,
    0.0,
    0.0,
    0.0,
    0.0,
    0.0,
    0.0,
    0.0,
    0.0,
    -0.0,
    -0.0,
    -0.0,
    -0.0,
    -0.0,
    -0.0,
    -0.0,
    -0.0,
    -0.0,
    -0.0,
    -0.0,
    -0.0,
    -0.0,
    -0.0,
    -0.0,
    -0.0,
    -0.0,
    -0.0,
    -0.0,
    -0.0,
    -0.0,
    -0.0,
    -0.0,
    -0.0,
    -0.0,
    -0.0,
    -0.0,
    -0.0,
    -0.0,
    -0.0,
    -0.0,
    -0.0,
    -0.0,
    -0.0,
    -0.0,
    -0.0,
    -0.0,
    -0.0,
    -0.0,
    -0.0,
    -0.0,
    -0.0,
    -0.0,
    -0.0,
    -0.0,
    -0.0,
    -0.0,
    -0.0,
    -0.0,
    -0.0,
    -0.0,
    -0.0,
    -0.0,
    -0.0,
    -0.0,
    -0.0,
    -0.0,
    -0.0,
    -0.0,
    -0.0,
    -0.0,
    -0.0,
    -0.0,
    -0.0,
    -0.0,
    -0.0,
    -0.0,
    -0.0,
    -0.0,
    -0.0,
    -0.0,
    -0.0,
    -0.0,
    -0.0,
    -0.0,
    -0.0,
    -0.0,
    -0.0,
    -0.0,
    -0.0,
    -0.0,
    -0.0,
    -0.0,
    -0.0,
    -0.0,
    0.0,
    0.0,
    0.0,
    0.0,
    0.0,
    0.0,
    0.0,
    0.0,
    0.0,
    0.0,
    0.0,
    0.0,
    0.0,
    0.0,
    0.0,
    0.0,
    0.0,
    0.0,
    0.0,
    0.0,
    0.0,
    0.0,
    0.0,
    0.0,
    0.0,
    0.0,
    0.0,
    0.0,
    0.0,
    0.0,
    0.0,
    0.0,
    0.0,
    0.0,
    0.0,
    0.0,
    0.0,
    0.0,
    0.0,
    0.0,
    0.0,
    0.0,
    0.0,
    0.0,
    0.0,
    0.0,
    0.0,
    0.0,
    0.0,
    0.0,
    0.0,
    0.0,
    0.0,
    0.0,
    0.0,
    0.0,
    -0.0,
    -0.0,
    -0.0,
    -0.0,
    -0.0,
    -0.0,
    -0.0,
    -0.0,
    -0.0,
    -0.0,
    -0.0,
    0.0,
    0.0,
    0.0,
    0.0,
    0.0,
    0.0,
    0.0,
    0.0,
    0.0,
    0.0,
    0.0,
    0.0,
    0.0,
    0.0,
    0.0,
    0.0,
    0.0,
    0.0,
    0.0,
    0.0,
    0.0,
    0.0,
    0.0,
    0.0,
    0.0,
    0.0,
    0.0,
    0.0,
    0.0,
    0.0,
    0.0,
    0.0,
    0.0,
    0.0,
    0.0,
    0.0,
    0.0,
    0.0,
    0.0,
    0.0,
    0.0,
    0.0,
    0.0,
    0.0,
    0.0,
    0.0,
    0.0,
    0.0,
    0.0,
    0.0,
    0.0,
    0.0,
    0.0,
    0.0,
    0.0,
    0.0,
    0.0,
    0.0,
    0.0,
    0.0,
    0.0,
    0.0,
    0.0,
    0.0,
    0.0,
    0.0,
    0.0,
    0.0,
    0.0,
    0.0,
    0.0,
    0.0,
    0.0,
    0.0,
    0.0,
    0.0,
    0.0,
    0.0,
    0.0,
    0.0,
    0.0,
    0.0,
    0.0,
    0.0,
    0.0,
    0.0,
    0.0,
    -0.0,
    -0.0,
    -0.0,
    -0.0,
    -0.0,
    -0.0,
    -0.0,
    -0.0,
    -0.0,
    -0.0,
    -0.0,
    -0.0,
    -0.0,
    -0.0,
    -0.0,
    -0.0,
    -0.0,
    -0.0,
    -0.0,
    -0.0,
    -0.0,
    -0.0,
    -0.0,
    -0.0,
    -0.0,
    -0.0,
    -0.0,
    -0.0,
    -0.0,
    -0.0,
    -0.0,
    -0.0,
    -0.0,
    -0.0,
    -0.0,
    -0.0,
    -0.0,
    -0.0,
    -0.0,
    -0.0,
    -0.0,
    -0.0,
    -0.0,
    -0.0,
    -0.0,
    -0.0,
    -0.0,
    -0.0,
    -0.0,
    -0.0,
    -0.0,
    -0.0,
    -0.0,
    -0.0,
    -0.0,
    -0.0,
    -0.0,
    -0.0,
    -0.0,
    -0.0,
    -0.0,
    -0.0,
    -0.0,
    -0.0,
    0.0,
    0.0,
    0.0,
    0.0,
    0.0,
    0.0,
    0.0,
    0.0,
    0.0,
    -0.0,
    -0.0,
    -0.0,
    -0.0,
    -0.0,
    -0.0,
    -0.0,
    -0.0,
    -0.0,
    -0.0,
    -0.0,
    -0.0,
    -0.0,
    -0.0,
    -0.0,
    -0.0,
    -0.0,
    0.0,
    0.0,
    0.0,
    0.0,
    0.0,
    0.0,
    0.0,
    0.0,
    0.0,
    0.0,
    0.0,
    0.0,
    0.0,
    0.0,
    0.0,
    0.0,
    0.0,
    0.0,
    0.0,
    0.0,
    0.0,
    0.0,
    0.0,
    0.0,
    0.0,
    0.0,
    0.0,
    0.0,
    0.0,
    0.0,
    0.0,
    0.0,
    0.0,
    0.0,
    0.0,
    0.0,
    0.0,
    0.0,
    0.0,
    0.0,
    0.0,
    0.0,
    0.0,
    0.0,
    0.0,
    0.0,
    0.0,
    0.0,
    0.0,
    0.0,
    0.0,
    0.0,
    0.0,
    0.0,
    0.0,
    0.0,
    0.0,
    -0.0,
    0.0,
    0.0,
    0.0,
    0.0,
    0.0,
    0.0,
    0.0,
    0.0,
    0.0,
    0.0,
    0.0,
    0.0,
    0.0,
    0.0,
    0.0,
    0.0,
    0.0,
    0.0,
    0.0,
    0.0,
    0.0,
    0.0,
    0.0,
    0.0,
    0.0,
    0.0,
    0.0,
    0.0,
    0.0,
    0.0,
    0.0,
    0.0,
    0.0,
    0.0,
    0.0,
    0.0,
    0.0,
    0.0,
    0.0,
    0.0,
    0.0,
    0.0,
    0.0,
    0.0,
    0.0,
    0.0,
    0.0,
    0.0,
    0.0,
    0.0,
    0.0,
    0.0,
    0.0,
    0.0,
    0.0,
    0.0,
    0.0,
    0.0,
    0.0,
    0.0,
    0.0,
    0.0,
    0.0,
    0.0,
    0.0,
    0.0,
    0.0,
    0.0,
    0.0,
    0.0,
    0.0,
    0.0,
    0.0,
    0.0,
    0.0,
    0.0,
    0.0,
    0.0,
    0.0,
    0.0,
    0.0,
    0.0,
    0.0,
    0.0,
    0.0,
    0.0,
    0.0,
    0.0,
    0.0,
    0.0,
    0.0,
    0.0,
    0.0,
    0.0,
    0.0,
    0.0,
    0.0,
    0.0,
    0.0,
    0.0,
    0.0,
    0.0,
    0.0,
    0.0,
    0.0,
    0.0,
    0.0,
    0.0,
    -0.0,
    -0.0,
    -0.0,
    -0.0,
    -0.0,
    -0.0,
    -0.0,
    -0.0,
    -0.0,
    -0.0,
    -0.0,
    -0.0,
    -0.0,
    -0.0,
    -0.0,
    -0.0,
    -0.0,
    -0.0,
    -0.0,
    -0.0,
    -0.0,
    -0.0,
    -0.0,
    -0.0,
    -0.0,
    -0.0,
    -0.0,
    -0.0,
    -0.0,
    -0.0,
    -0.0,
    -0.0,
    -0.0,
    -0.0,
    -0.0,
    -0.0,
    -0.0,
    -0.0,
    -0.0,
    -0.0,
    -0.0,
    -0.0,
    -0.0,
    -0.0,
    -0.0,
    -0.0,
    -0.0,
    -0.0,
    -0.0,
    -0.0,
    -0.0,
    -0.0,
    -0.0,
    -0.0,
    -0.0,
    0.0,
    0.0,
    0.0,
    0.0,
    0.0,
    0.0,
    0.0,
    0.0,
    0.0,
    0.0,
    0.0,
    0.0,
    0.0,
    0.0,
    0.0,
    0.0,
    0.0,
    0.0,
    0.0,
    0.0,
    0.0,
    0.0,
    0.0,
    0.0,
    0.0,
    0.0,
    0.0,
    0.0,
    0.0,
    0.0,
    0.0,
    0.0,
    0.0,
    0.0,
    0.0,
    0.0,
    0.0,
    0.0,
    0.0,
    0.0,
    0.0,
    0.0,
    0.0,
    0.0,
    0.0,
    0.0,
    0.0,
    0.0,
    0.0,
    0.0,
    0.0,
    0.0,
    0.0,
    0.0,
    -0.0,
    -0.0,
    -0.0,
    -0.0,
    -0.0,
    -0.0,
    -0.0,
    -0.0,
    -0.0,
    -0.0,
    -0.0,
    -0.0,
    -0.0,
    -0.0,
    -0.0,
    -0.0,
    -0.0,
    -0.0,
    -0.0,
    -0.0,
    -0.0,
    -0.0,
    -0.0,
    -0.0,
    -0.0,
    -0.0,
    -0.0,
    -0.0,
    -0.0,
    -0.0,
    -0.0,
    -0.0,
    -0.0,
    -0.0,
    -0.0,
    -0.0,
    -0.0,
    -0.0,
    -0.0,
    -0.0,
    -0.0,
    -0.0,
    -0.0,
    -0.0,
    -0.0,
    -0.0,
    -0.0,
    -0.0,
    -0.0,
    -0.0,
    -0.0,
    -0.0,
    -0.0,
    -0.0,
    -0.0,
    -0.0,
    -0.0,
    -0.0,
    -0.0,
    -0.0,
    -0.0,
    -0.0,
    -0.0,
    -0.0,
    -0.0,
    -0.0,
    -0.0,
    -0.0,
    -0.0,
    -0.0,
    -0.0,
    -0.0,
    -0.0,
    -0.0,
    -0.0,
    -0.0,
    -0.0,
    -0.0,
    -0.0,
    -0.0,
    -0.0,
    -0.0,
    -0.0,
    -0.0,
    -0.0,
    -0.0,
    -0.0,
    -0.0,
    -0.0,
    -0.0,
    -0.0,
    -0.0,
    -0.0,
    -0.0,
    -0.0,
    -0.0,
    -0.0,
    -0.0,
    -0.0,
    -0.0,
    -0.0,
    -0.0,
    -0.0,
    -0.0,
    -0.0,
    -0.0,
    -0.0,
    -0.0,
    -0.0,
    -0.0,
    -0.0,
    -0.0,
    -0.0,
    -0.0,
    -0.0,
    -0.0,
    -0.0,
    -0.0,
    -0.0,
    -0.0,
    -0.0,
    -0.0,
    -0.0,
    -0.0,
    -0.0,
    -0.0,
    -0.0,
    -0.0,
    -0.0,
    -0.0,
    -0.0,
    -0.0,
    -0.0,
    -0.0,
    -0.0,
    -0.0,
    -0.0,
    -0.0,
    -0.0,
    -0.0,
    -0.0,
    -0.0,
    -0.0,
    -0.0,
    -0.0,
    -0.0,
    -0.0,
    -0.0,
    -0.0,
    -0.0,
    -0.0,
    -0.0,
    -0.0,
    -0.0,
    -0.0,
    -0.0,
    -0.0,
    -0.0,
    -0.0,
    -0.0,
    -0.0,
    -0.0,
    -0.0,
    -0.0,
    -0.0,
    -0.0,
    -0.0
  ],
  "debug": {
    "wx_key": {
      "ts_hour": null,
      "lat": null,
      "lon": null
    },
    "wx_ts_hour_in": null,
    "wx_ts_epoch": null,
    "reason": "ok",
    "force_recompute": true,
    "persist_ignored": true,
    "ignored_persist": true,
    "used_fallback": false,
    "weather_applied": false,
    "weather_source": "neutral",
    "estimat_cfg_used": {
      "force": true
    },
    "input_candidates": {
      "debug_session": "C:\\Users\\easy2\\OneDrive\\Skrivebord\\Archieve\\Karriere\\CycleGraph\\_debug\\session_16127771071.json",
      "debug_result": "C:\\Users\\easy2\\OneDrive\\Skrivebord\\Archieve\\Karriere\\CycleGraph\\_debug\\result_16127771071.json",
      "results": "C:\\Users\\easy2\\OneDrive\\Skrivebord\\Archieve\\Karriere\\CycleGraph\\logs\\results\\result_16127771071.json",
      "inline_samples": "C:\\Users\\easy2\\OneDrive\\Skrivebord\\Archieve\\Karriere\\CycleGraph\\logs\\inline_samples_16127771071.json",
      "actual10_latest_session": "C:\\Users\\easy2\\OneDrive\\Skrivebord\\Archieve\\Karriere\\CycleGraph\\logs\\actual10\\latest\\session_16127771071.json",
      "raw_streams": "C:\\Users\\easy2\\OneDrive\\Skrivebord\\Archieve\\Karriere\\CycleGraph\\data\\raw\\streams_16127771071.json",
      "raw_activity": "C:\\Users\\easy2\\OneDrive\\Skrivebord\\Archieve\\Karriere\\CycleGraph\\data\\raw\\activity_16127771071.json",
      "gpx": "C:\\Users\\easy2\\OneDrive\\Skrivebord\\Archieve\\Karriere\\CycleGraph\\data\\gpx\\16127771071.gpx"
    },
    "input_exists": {
      "debug_session": true,
      "debug_result": true,
      "results": true,
      "inline_samples": false,
      "actual10_latest_session": true,
      "raw_streams": false,
      "raw_activity": false,
      "gpx": false
    },
    "input_used": "C:\\Users\\easy2\\OneDrive\\Skrivebord\\Archieve\\Karriere\\CycleGraph\\_debug\\session_16127771071.json",
    "samples_len": 1717,
    "streams_probe": null
  },
  "repr_kind": "object_v3",
  "weather_source": "neutral",
  "profile_version": "v1-883d8daf-20251228",
  "profile_used": {
    "rider_weight_kg": 78.0,
    "bike_weight_kg": 8.0,
    "weight_kg": 86.0,
    "total_weight_kg": 86.0,
    "cda": 0.3,
    "crr": 0.004,
    "crank_eff_pct": 95.5,
    "device": "strava",
    "notes": "Trinn5 default; rediger fritt.",
    "profile_version": "v1-883d8daf-20251228"
  },
  "start_time": "2025-11-19T08:00:39.249703"
}